{
    "Meta Data": {
        "1. Information": "Daily Prices (open, high, low, close) and Volumes",
        "2. Symbol": "DIDIY",
        "3. Last Refreshed": "2024-07-25",
        "4. Output Size": "Full size",
        "5. Time Zone": "US/Eastern"
    },
    "Time Series (Daily)": {
        "2024-07-25": {
            "1. open": "3.5100",
            "2. high": "3.5200",
            "3. low": "3.3900",
            "4. close": "3.4900",
            "5. volume": "8656939"
        },
        "2024-07-24": {
            "1. open": "3.6200",
            "2. high": "3.6400",
            "3. low": "3.5200",
            "4. close": "3.5200",
            "5. volume": "4327270"
        },
        "2024-07-23": {
            "1. open": "3.6200",
            "2. high": "3.6700",
            "3. low": "3.5700",
            "4. close": "3.6400",
            "5. volume": "3846852"
        },
        "2024-07-22": {
            "1. open": "3.6300",
            "2. high": "3.6600",
            "3. low": "3.5900",
            "4. close": "3.6200",
            "5. volume": "3177472"
        },
        "2024-07-19": {
            "1. open": "3.5500",
            "2. high": "3.6000",
            "3. low": "3.5400",
            "4. close": "3.5600",
            "5. volume": "2194221"
        },
        "2024-07-18": {
            "1. open": "3.6200",
            "2. high": "3.6700",
            "3. low": "3.5500",
            "4. close": "3.5700",
            "5. volume": "8179793"
        },
        "2024-07-17": {
            "1. open": "3.6800",
            "2. high": "3.6800",
            "3. low": "3.6200",
            "4. close": "3.6600",
            "5. volume": "7235866"
        },
        "2024-07-16": {
            "1. open": "3.7000",
            "2. high": "3.7700",
            "3. low": "3.6600",
            "4. close": "3.6850",
            "5. volume": "16945363"
        },
        "2024-07-15": {
            "1. open": "3.7000",
            "2. high": "3.7800",
            "3. low": "3.6900",
            "4. close": "3.7100",
            "5. volume": "7590278"
        },
        "2024-07-12": {
            "1. open": "3.6100",
            "2. high": "3.7700",
            "3. low": "3.5400",
            "4. close": "3.7500",
            "5. volume": "25490383"
        },
        "2024-07-11": {
            "1. open": "3.7700",
            "2. high": "3.8300",
            "3. low": "3.5000",
            "4. close": "3.5200",
            "5. volume": "28759672"
        },
        "2024-07-10": {
            "1. open": "3.9500",
            "2. high": "3.9800",
            "3. low": "3.6900",
            "4. close": "3.7500",
            "5. volume": "19046624"
        },
        "2024-07-09": {
            "1. open": "3.9800",
            "2. high": "4.0200",
            "3. low": "3.9700",
            "4. close": "3.9900",
            "5. volume": "3578595"
        },
        "2024-07-08": {
            "1. open": "3.9800",
            "2. high": "4.0100",
            "3. low": "3.9600",
            "4. close": "4.0000",
            "5. volume": "3854180"
        },
        "2024-07-05": {
            "1. open": "4.0300",
            "2. high": "4.0500",
            "3. low": "3.9500",
            "4. close": "4.0000",
            "5. volume": "6926517"
        },
        "2024-07-03": {
            "1. open": "4.0600",
            "2. high": "4.1300",
            "3. low": "4.0500",
            "4. close": "4.0900",
            "5. volume": "5429607"
        },
        "2024-07-02": {
            "1. open": "3.9600",
            "2. high": "4.1600",
            "3. low": "3.9500",
            "4. close": "4.1400",
            "5. volume": "7408530"
        },
        "2024-07-01": {
            "1. open": "4.1900",
            "2. high": "4.1950",
            "3. low": "3.9500",
            "4. close": "4.0200",
            "5. volume": "16120479"
        },
        "2024-06-28": {
            "1. open": "4.2400",
            "2. high": "4.2700",
            "3. low": "4.0475",
            "4. close": "4.1400",
            "5. volume": "11097901"
        },
        "2024-06-27": {
            "1. open": "4.3300",
            "2. high": "4.3400",
            "3. low": "4.2100",
            "4. close": "4.2300",
            "5. volume": "7177658"
        },
        "2024-06-26": {
            "1. open": "4.3800",
            "2. high": "4.4800",
            "3. low": "4.3200",
            "4. close": "4.3500",
            "5. volume": "3770261"
        },
        "2024-06-25": {
            "1. open": "4.3800",
            "2. high": "4.4400",
            "3. low": "4.3500",
            "4. close": "4.4000",
            "5. volume": "6279971"
        },
        "2024-06-24": {
            "1. open": "4.4100",
            "2. high": "4.4600",
            "3. low": "4.3500",
            "4. close": "4.4000",
            "5. volume": "6976166"
        },
        "2024-06-21": {
            "1. open": "4.3800",
            "2. high": "4.4500",
            "3. low": "4.3800",
            "4. close": "4.4400",
            "5. volume": "3601957"
        },
        "2024-06-20": {
            "1. open": "4.5000",
            "2. high": "4.5000",
            "3. low": "4.3250",
            "4. close": "4.4200",
            "5. volume": "7905610"
        },
        "2024-06-18": {
            "1. open": "4.3600",
            "2. high": "4.5000",
            "3. low": "4.3450",
            "4. close": "4.4900",
            "5. volume": "5643766"
        },
        "2024-06-17": {
            "1. open": "4.4050",
            "2. high": "4.4500",
            "3. low": "4.3200",
            "4. close": "4.4500",
            "5. volume": "10900475"
        },
        "2024-06-14": {
            "1. open": "4.2300",
            "2. high": "4.3400",
            "3. low": "4.2300",
            "4. close": "4.2600",
            "5. volume": "3185554"
        },
        "2024-06-13": {
            "1. open": "4.2100",
            "2. high": "4.3500",
            "3. low": "4.2100",
            "4. close": "4.3000",
            "5. volume": "6414043"
        },
        "2024-06-12": {
            "1. open": "4.3200",
            "2. high": "4.3600",
            "3. low": "4.1300",
            "4. close": "4.2200",
            "5. volume": "17493750"
        },
        "2024-06-11": {
            "1. open": "4.3300",
            "2. high": "4.4000",
            "3. low": "4.2700",
            "4. close": "4.3300",
            "5. volume": "4460248"
        },
        "2024-06-10": {
            "1. open": "4.3000",
            "2. high": "4.3760",
            "3. low": "4.2800",
            "4. close": "4.3200",
            "5. volume": "7067960"
        },
        "2024-06-07": {
            "1. open": "4.3400",
            "2. high": "4.4500",
            "3. low": "4.3000",
            "4. close": "4.3100",
            "5. volume": "7593100"
        },
        "2024-06-06": {
            "1. open": "4.4300",
            "2. high": "4.5000",
            "3. low": "4.3000",
            "4. close": "4.3000",
            "5. volume": "4877687"
        },
        "2024-06-05": {
            "1. open": "4.5300",
            "2. high": "4.5500",
            "3. low": "4.2400",
            "4. close": "4.4500",
            "5. volume": "10425874"
        },
        "2024-06-04": {
            "1. open": "4.6200",
            "2. high": "4.6300",
            "3. low": "4.5600",
            "4. close": "4.5800",
            "5. volume": "7603710"
        },
        "2024-06-03": {
            "1. open": "4.5930",
            "2. high": "4.6300",
            "3. low": "4.5500",
            "4. close": "4.6000",
            "5. volume": "6146561"
        },
        "2024-05-31": {
            "1. open": "4.5800",
            "2. high": "4.6050",
            "3. low": "4.4900",
            "4. close": "4.5800",
            "5. volume": "6615615"
        },
        "2024-05-30": {
            "1. open": "4.6300",
            "2. high": "4.6400",
            "3. low": "4.5700",
            "4. close": "4.6000",
            "5. volume": "4465352"
        },
        "2024-05-29": {
            "1. open": "4.5800",
            "2. high": "4.7000",
            "3. low": "4.5700",
            "4. close": "4.6000",
            "5. volume": "23620182"
        },
        "2024-05-28": {
            "1. open": "4.6400",
            "2. high": "4.7200",
            "3. low": "4.6100",
            "4. close": "4.6100",
            "5. volume": "6593943"
        },
        "2024-05-24": {
            "1. open": "4.6500",
            "2. high": "4.7600",
            "3. low": "4.6500",
            "4. close": "4.6500",
            "5. volume": "3883412"
        },
        "2024-05-23": {
            "1. open": "4.6900",
            "2. high": "4.7100",
            "3. low": "4.6400",
            "4. close": "4.6700",
            "5. volume": "3516785"
        },
        "2024-05-22": {
            "1. open": "4.7400",
            "2. high": "4.8000",
            "3. low": "4.6625",
            "4. close": "4.7100",
            "5. volume": "2065201"
        },
        "2024-05-21": {
            "1. open": "4.7400",
            "2. high": "4.7900",
            "3. low": "4.6700",
            "4. close": "4.7000",
            "5. volume": "2331685"
        },
        "2024-05-20": {
            "1. open": "4.7700",
            "2. high": "4.8300",
            "3. low": "4.6600",
            "4. close": "4.8000",
            "5. volume": "4598368"
        },
        "2024-05-17": {
            "1. open": "4.5600",
            "2. high": "4.7900",
            "3. low": "4.5000",
            "4. close": "4.7800",
            "5. volume": "6169560"
        },
        "2024-05-16": {
            "1. open": "4.7199",
            "2. high": "4.8800",
            "3. low": "4.6000",
            "4. close": "4.6065",
            "5. volume": "5766494"
        },
        "2024-05-15": {
            "1. open": "4.8200",
            "2. high": "4.8300",
            "3. low": "4.6100",
            "4. close": "4.6700",
            "5. volume": "5044220"
        },
        "2024-05-14": {
            "1. open": "4.7500",
            "2. high": "4.8235",
            "3. low": "4.5800",
            "4. close": "4.8100",
            "5. volume": "8033281"
        },
        "2024-05-13": {
            "1. open": "4.9100",
            "2. high": "4.9400",
            "3. low": "4.7700",
            "4. close": "4.7900",
            "5. volume": "6020023"
        },
        "2024-05-10": {
            "1. open": "4.9101",
            "2. high": "4.9500",
            "3. low": "4.8500",
            "4. close": "4.9000",
            "5. volume": "4503242"
        },
        "2024-05-09": {
            "1. open": "4.9400",
            "2. high": "4.9500",
            "3. low": "4.8800",
            "4. close": "4.9000",
            "5. volume": "4116264"
        },
        "2024-05-08": {
            "1. open": "4.9100",
            "2. high": "4.9600",
            "3. low": "4.8500",
            "4. close": "4.8600",
            "5. volume": "5025425"
        },
        "2024-05-07": {
            "1. open": "4.9800",
            "2. high": "4.9900",
            "3. low": "4.9300",
            "4. close": "4.9500",
            "5. volume": "4120961"
        },
        "2024-05-06": {
            "1. open": "5.0600",
            "2. high": "5.1000",
            "3. low": "4.9600",
            "4. close": "5.0000",
            "5. volume": "6955706"
        },
        "2024-05-03": {
            "1. open": "5.1200",
            "2. high": "5.1300",
            "3. low": "5.0100",
            "4. close": "5.0300",
            "5. volume": "4205201"
        },
        "2024-05-02": {
            "1. open": "4.9600",
            "2. high": "5.1600",
            "3. low": "4.9600",
            "4. close": "5.1400",
            "5. volume": "10162184"
        },
        "2024-05-01": {
            "1. open": "4.9200",
            "2. high": "4.9300",
            "3. low": "4.8300",
            "4. close": "4.9100",
            "5. volume": "9476773"
        },
        "2024-04-30": {
            "1. open": "5.0100",
            "2. high": "5.0100",
            "3. low": "4.8500",
            "4. close": "4.9400",
            "5. volume": "9184584"
        },
        "2024-04-29": {
            "1. open": "5.0200",
            "2. high": "5.0400",
            "3. low": "4.8100",
            "4. close": "4.9800",
            "5. volume": "11688585"
        },
        "2024-04-26": {
            "1. open": "4.9600",
            "2. high": "5.1600",
            "3. low": "4.9500",
            "4. close": "5.0200",
            "5. volume": "21149316"
        },
        "2024-04-25": {
            "1. open": "4.9200",
            "2. high": "4.9400",
            "3. low": "4.7600",
            "4. close": "4.9300",
            "5. volume": "7432336"
        },
        "2024-04-24": {
            "1. open": "4.8800",
            "2. high": "5.0000",
            "3. low": "4.8800",
            "4. close": "4.9200",
            "5. volume": "14087913"
        },
        "2024-04-23": {
            "1. open": "4.7900",
            "2. high": "4.8800",
            "3. low": "4.7700",
            "4. close": "4.8300",
            "5. volume": "8476920"
        },
        "2024-04-22": {
            "1. open": "4.4700",
            "2. high": "4.8000",
            "3. low": "4.4700",
            "4. close": "4.7200",
            "5. volume": "7864494"
        },
        "2024-04-19": {
            "1. open": "4.6800",
            "2. high": "4.7400",
            "3. low": "4.3800",
            "4. close": "4.4200",
            "5. volume": "4986664"
        },
        "2024-04-18": {
            "1. open": "4.6001",
            "2. high": "4.7500",
            "3. low": "4.6000",
            "4. close": "4.6600",
            "5. volume": "4696703"
        },
        "2024-04-17": {
            "1. open": "4.4200",
            "2. high": "4.6600",
            "3. low": "4.4200",
            "4. close": "4.6400",
            "5. volume": "8334115"
        },
        "2024-04-16": {
            "1. open": "4.5900",
            "2. high": "4.6500",
            "3. low": "4.2600",
            "4. close": "4.4600",
            "5. volume": "12595883"
        },
        "2024-04-15": {
            "1. open": "4.8000",
            "2. high": "4.8200",
            "3. low": "4.5800",
            "4. close": "4.6600",
            "5. volume": "10010878"
        },
        "2024-04-12": {
            "1. open": "5.0000",
            "2. high": "5.0500",
            "3. low": "4.7700",
            "4. close": "4.8100",
            "5. volume": "21763977"
        },
        "2024-04-11": {
            "1. open": "4.7600",
            "2. high": "5.0900",
            "3. low": "4.7600",
            "4. close": "4.9200",
            "5. volume": "33874515"
        },
        "2024-04-10": {
            "1. open": "4.4700",
            "2. high": "4.8400",
            "3. low": "4.4300",
            "4. close": "4.8000",
            "5. volume": "23244441"
        },
        "2024-04-09": {
            "1. open": "4.3600",
            "2. high": "4.5300",
            "3. low": "4.3500",
            "4. close": "4.4400",
            "5. volume": "17861998"
        },
        "2024-04-08": {
            "1. open": "4.4100",
            "2. high": "4.4900",
            "3. low": "4.3500",
            "4. close": "4.4200",
            "5. volume": "19306955"
        },
        "2024-04-05": {
            "1. open": "4.0200",
            "2. high": "4.4200",
            "3. low": "4.0100",
            "4. close": "4.4200",
            "5. volume": "19185873"
        },
        "2024-04-04": {
            "1. open": "3.9500",
            "2. high": "4.0000",
            "3. low": "3.9200",
            "4. close": "3.9500",
            "5. volume": "3545989"
        },
        "2024-04-03": {
            "1. open": "3.9800",
            "2. high": "3.9900",
            "3. low": "3.9300",
            "4. close": "3.9600",
            "5. volume": "11660120"
        },
        "2024-04-02": {
            "1. open": "3.9700",
            "2. high": "4.0500",
            "3. low": "3.9300",
            "4. close": "3.9875",
            "5. volume": "9314089"
        },
        "2024-04-01": {
            "1. open": "3.8400",
            "2. high": "3.9900",
            "3. low": "3.8200",
            "4. close": "3.9880",
            "5. volume": "9314089"
        },
        "2024-03-28": {
            "1. open": "3.8200",
            "2. high": "3.8600",
            "3. low": "3.7700",
            "4. close": "3.8300",
            "5. volume": "7730126"
        },
        "2024-03-27": {
            "1. open": "3.7300",
            "2. high": "3.8900",
            "3. low": "3.6700",
            "4. close": "3.8100",
            "5. volume": "13893174"
        },
        "2024-03-26": {
            "1. open": "3.9000",
            "2. high": "3.9900",
            "3. low": "3.7200",
            "4. close": "3.7200",
            "5. volume": "11063051"
        },
        "2024-03-25": {
            "1. open": "3.9200",
            "2. high": "4.0200",
            "3. low": "3.8800",
            "4. close": "3.9000",
            "5. volume": "12668236"
        },
        "2024-03-22": {
            "1. open": "3.9400",
            "2. high": "4.0000",
            "3. low": "3.8900",
            "4. close": "3.9200",
            "5. volume": "7343288"
        },
        "2024-03-21": {
            "1. open": "3.9400",
            "2. high": "4.0100",
            "3. low": "3.9000",
            "4. close": "3.9700",
            "5. volume": "7622190"
        },
        "2024-03-20": {
            "1. open": "3.8500",
            "2. high": "3.9900",
            "3. low": "3.8400",
            "4. close": "3.9900",
            "5. volume": "10541491"
        },
        "2024-03-19": {
            "1. open": "3.7600",
            "2. high": "3.8800",
            "3. low": "3.7500",
            "4. close": "3.8800",
            "5. volume": "3712910"
        },
        "2024-03-18": {
            "1. open": "3.8200",
            "2. high": "3.8700",
            "3. low": "3.7800",
            "4. close": "3.8400",
            "5. volume": "3168652"
        },
        "2024-03-15": {
            "1. open": "3.8300",
            "2. high": "3.9000",
            "3. low": "3.8000",
            "4. close": "3.8500",
            "5. volume": "3313312"
        },
        "2024-03-14": {
            "1. open": "3.9500",
            "2. high": "3.9600",
            "3. low": "3.8200",
            "4. close": "3.9200",
            "5. volume": "8623092"
        },
        "2024-03-13": {
            "1. open": "3.9100",
            "2. high": "3.9800",
            "3. low": "3.8800",
            "4. close": "3.9300",
            "5. volume": "8526975"
        },
        "2024-03-12": {
            "1. open": "3.8900",
            "2. high": "4.0100",
            "3. low": "3.8700",
            "4. close": "3.8800",
            "5. volume": "4368245"
        },
        "2024-03-11": {
            "1. open": "3.8000",
            "2. high": "3.8900",
            "3. low": "3.7500",
            "4. close": "3.8800",
            "5. volume": "4367538"
        },
        "2024-03-08": {
            "1. open": "3.8500",
            "2. high": "3.8600",
            "3. low": "3.7800",
            "4. close": "3.8000",
            "5. volume": "4434091"
        },
        "2024-03-07": {
            "1. open": "3.8200",
            "2. high": "3.9000",
            "3. low": "3.8000",
            "4. close": "3.8700",
            "5. volume": "3815697"
        },
        "2024-03-06": {
            "1. open": "3.8300",
            "2. high": "3.9200",
            "3. low": "3.8200",
            "4. close": "3.9100",
            "5. volume": "6113030"
        },
        "2024-03-05": {
            "1. open": "3.7600",
            "2. high": "3.8500",
            "3. low": "3.7200",
            "4. close": "3.8300",
            "5. volume": "8137464"
        },
        "2024-03-04": {
            "1. open": "3.7100",
            "2. high": "3.8500",
            "3. low": "3.6665",
            "4. close": "3.7800",
            "5. volume": "7757952"
        },
        "2024-03-01": {
            "1. open": "3.7900",
            "2. high": "3.8300",
            "3. low": "3.6400",
            "4. close": "3.7000",
            "5. volume": "3578145"
        },
        "2024-02-29": {
            "1. open": "3.8100",
            "2. high": "3.8500",
            "3. low": "3.7400",
            "4. close": "3.7700",
            "5. volume": "3317834"
        },
        "2024-02-28": {
            "1. open": "3.8600",
            "2. high": "3.8800",
            "3. low": "3.7600",
            "4. close": "3.8100",
            "5. volume": "2703987"
        },
        "2024-02-27": {
            "1. open": "3.9100",
            "2. high": "3.9700",
            "3. low": "3.8600",
            "4. close": "3.9000",
            "5. volume": "5248506"
        },
        "2024-02-26": {
            "1. open": "3.7300",
            "2. high": "3.9300",
            "3. low": "3.7200",
            "4. close": "3.9100",
            "5. volume": "6047165"
        },
        "2024-02-23": {
            "1. open": "3.7100",
            "2. high": "4.0300",
            "3. low": "3.6500",
            "4. close": "3.7600",
            "5. volume": "14637126"
        },
        "2024-02-22": {
            "1. open": "3.7200",
            "2. high": "3.7400",
            "3. low": "3.6000",
            "4. close": "3.6700",
            "5. volume": "2882308"
        },
        "2024-02-21": {
            "1. open": "3.7200",
            "2. high": "3.7400",
            "3. low": "3.6300",
            "4. close": "3.7000",
            "5. volume": "2036939"
        },
        "2024-02-20": {
            "1. open": "3.6900",
            "2. high": "3.7600",
            "3. low": "3.6500",
            "4. close": "3.6600",
            "5. volume": "2393485"
        },
        "2024-02-16": {
            "1. open": "3.6200",
            "2. high": "3.7800",
            "3. low": "3.6200",
            "4. close": "3.7700",
            "5. volume": "9480943"
        },
        "2024-02-15": {
            "1. open": "3.5600",
            "2. high": "3.7300",
            "3. low": "3.5500",
            "4. close": "3.6100",
            "5. volume": "5237236"
        },
        "2024-02-14": {
            "1. open": "3.4300",
            "2. high": "3.6500",
            "3. low": "3.3700",
            "4. close": "3.6200",
            "5. volume": "6457127"
        },
        "2024-02-13": {
            "1. open": "3.4400",
            "2. high": "3.4500",
            "3. low": "3.3300",
            "4. close": "3.3600",
            "5. volume": "2582483"
        },
        "2024-02-12": {
            "1. open": "3.4900",
            "2. high": "3.6200",
            "3. low": "3.4200",
            "4. close": "3.4800",
            "5. volume": "2264213"
        },
        "2024-02-09": {
            "1. open": "3.4900",
            "2. high": "3.5900",
            "3. low": "3.4800",
            "4. close": "3.5600",
            "5. volume": "1344362"
        },
        "2024-02-08": {
            "1. open": "3.4600",
            "2. high": "3.5700",
            "3. low": "3.4600",
            "4. close": "3.5350",
            "5. volume": "1915393"
        },
        "2024-02-07": {
            "1. open": "3.4000",
            "2. high": "3.5700",
            "3. low": "3.3000",
            "4. close": "3.5200",
            "5. volume": "5139916"
        },
        "2024-02-06": {
            "1. open": "3.2700",
            "2. high": "3.5400",
            "3. low": "3.2500",
            "4. close": "3.4500",
            "5. volume": "4917911"
        },
        "2024-02-05": {
            "1. open": "3.2600",
            "2. high": "3.3100",
            "3. low": "3.1400",
            "4. close": "3.1700",
            "5. volume": "10387313"
        },
        "2024-02-02": {
            "1. open": "3.4700",
            "2. high": "3.4700",
            "3. low": "3.3300",
            "4. close": "3.3404",
            "5. volume": "9753735"
        },
        "2024-02-01": {
            "1. open": "3.5400",
            "2. high": "3.6200",
            "3. low": "3.5100",
            "4. close": "3.5200",
            "5. volume": "3944306"
        },
        "2024-01-31": {
            "1. open": "3.4900",
            "2. high": "3.5300",
            "3. low": "3.4500",
            "4. close": "3.5000",
            "5. volume": "2636143"
        },
        "2024-01-30": {
            "1. open": "3.5600",
            "2. high": "3.5800",
            "3. low": "3.4800",
            "4. close": "3.5200",
            "5. volume": "5015014"
        },
        "2024-01-29": {
            "1. open": "3.7000",
            "2. high": "3.7200",
            "3. low": "3.5600",
            "4. close": "3.6100",
            "5. volume": "3449559"
        },
        "2024-01-26": {
            "1. open": "3.6500",
            "2. high": "3.7300",
            "3. low": "3.6150",
            "4. close": "3.7000",
            "5. volume": "3078889"
        },
        "2024-01-25": {
            "1. open": "3.6900",
            "2. high": "3.7400",
            "3. low": "3.6500",
            "4. close": "3.7100",
            "5. volume": "3537877"
        },
        "2024-01-24": {
            "1. open": "3.7400",
            "2. high": "3.8400",
            "3. low": "3.6600",
            "4. close": "3.6900",
            "5. volume": "4968870"
        },
        "2024-01-23": {
            "1. open": "3.5600",
            "2. high": "3.7000",
            "3. low": "3.5500",
            "4. close": "3.6800",
            "5. volume": "8843804"
        },
        "2024-01-22": {
            "1. open": "3.6400",
            "2. high": "3.6400",
            "3. low": "3.4700",
            "4. close": "3.5000",
            "5. volume": "9085196"
        },
        "2024-01-19": {
            "1. open": "3.7200",
            "2. high": "3.8300",
            "3. low": "3.7000",
            "4. close": "3.7100",
            "5. volume": "4898625"
        },
        "2024-01-18": {
            "1. open": "3.6900",
            "2. high": "3.8000",
            "3. low": "3.6800",
            "4. close": "3.7700",
            "5. volume": "5397214"
        },
        "2024-01-17": {
            "1. open": "3.7700",
            "2. high": "3.7800",
            "3. low": "3.6700",
            "4. close": "3.7000",
            "5. volume": "8172317"
        },
        "2024-01-16": {
            "1. open": "3.8500",
            "2. high": "3.9350",
            "3. low": "3.8500",
            "4. close": "3.9000",
            "5. volume": "6323287"
        },
        "2024-01-12": {
            "1. open": "3.8900",
            "2. high": "4.0300",
            "3. low": "3.8900",
            "4. close": "4.0300",
            "5. volume": "12427966"
        },
        "2024-01-11": {
            "1. open": "3.8800",
            "2. high": "3.9200",
            "3. low": "3.8600",
            "4. close": "3.9200",
            "5. volume": "3696883"
        },
        "2024-01-10": {
            "1. open": "3.8700",
            "2. high": "3.9000",
            "3. low": "3.8600",
            "4. close": "3.9000",
            "5. volume": "2869788"
        },
        "2024-01-09": {
            "1. open": "3.9100",
            "2. high": "3.9600",
            "3. low": "3.8600",
            "4. close": "3.8900",
            "5. volume": "4934798"
        },
        "2024-01-08": {
            "1. open": "3.8800",
            "2. high": "3.9700",
            "3. low": "3.8200",
            "4. close": "3.9600",
            "5. volume": "5253529"
        },
        "2024-01-05": {
            "1. open": "3.9900",
            "2. high": "4.0000",
            "3. low": "3.9000",
            "4. close": "3.9500",
            "5. volume": "9219645"
        },
        "2024-01-04": {
            "1. open": "3.7700",
            "2. high": "4.0600",
            "3. low": "3.7700",
            "4. close": "4.0000",
            "5. volume": "7072341"
        },
        "2024-01-03": {
            "1. open": "3.8200",
            "2. high": "3.8500",
            "3. low": "3.7700",
            "4. close": "3.8000",
            "5. volume": "2704909"
        },
        "2024-01-02": {
            "1. open": "3.8700",
            "2. high": "3.9000",
            "3. low": "3.8200",
            "4. close": "3.8600",
            "5. volume": "2213402"
        },
        "2023-12-29": {
            "1. open": "3.9200",
            "2. high": "3.9700",
            "3. low": "3.8800",
            "4. close": "3.9500",
            "5. volume": "4459252"
        },
        "2023-12-28": {
            "1. open": "3.8500",
            "2. high": "3.9600",
            "3. low": "3.8100",
            "4. close": "3.9500",
            "5. volume": "3586560"
        },
        "2023-12-27": {
            "1. open": "3.7100",
            "2. high": "3.8800",
            "3. low": "3.7000",
            "4. close": "3.8800",
            "5. volume": "3055723"
        },
        "2023-12-26": {
            "1. open": "3.6600",
            "2. high": "3.7470",
            "3. low": "3.6600",
            "4. close": "3.7100",
            "5. volume": "2687216"
        },
        "2023-12-22": {
            "1. open": "3.5200",
            "2. high": "3.7800",
            "3. low": "3.5000",
            "4. close": "3.7300",
            "5. volume": "4934278"
        },
        "2023-12-21": {
            "1. open": "3.6600",
            "2. high": "3.6800",
            "3. low": "3.5700",
            "4. close": "3.5900",
            "5. volume": "3870535"
        },
        "2023-12-20": {
            "1. open": "3.7500",
            "2. high": "3.7600",
            "3. low": "3.6900",
            "4. close": "3.6900",
            "5. volume": "3869202"
        },
        "2023-12-19": {
            "1. open": "3.7500",
            "2. high": "3.7800",
            "3. low": "3.7200",
            "4. close": "3.7600",
            "5. volume": "6440603"
        },
        "2023-12-18": {
            "1. open": "3.7200",
            "2. high": "3.8400",
            "3. low": "3.7200",
            "4. close": "3.7800",
            "5. volume": "4612397"
        },
        "2023-12-15": {
            "1. open": "3.7100",
            "2. high": "3.8100",
            "3. low": "3.6800",
            "4. close": "3.8000",
            "5. volume": "3305311"
        },
        "2023-12-14": {
            "1. open": "3.6900",
            "2. high": "3.7500",
            "3. low": "3.6600",
            "4. close": "3.7200",
            "5. volume": "3251408"
        },
        "2023-12-13": {
            "1. open": "3.6100",
            "2. high": "3.7500",
            "3. low": "3.5800",
            "4. close": "3.7300",
            "5. volume": "4977312"
        },
        "2023-12-12": {
            "1. open": "3.6900",
            "2. high": "3.7100",
            "3. low": "3.6000",
            "4. close": "3.6300",
            "5. volume": "2598523"
        },
        "2023-12-11": {
            "1. open": "3.7400",
            "2. high": "3.7500",
            "3. low": "3.6600",
            "4. close": "3.6800",
            "5. volume": "2141478"
        },
        "2023-12-08": {
            "1. open": "3.7150",
            "2. high": "3.8200",
            "3. low": "3.7100",
            "4. close": "3.7700",
            "5. volume": "1236889"
        },
        "2023-12-07": {
            "1. open": "3.8600",
            "2. high": "3.8700",
            "3. low": "3.7200",
            "4. close": "3.8300",
            "5. volume": "1513299"
        },
        "2023-12-06": {
            "1. open": "3.7100",
            "2. high": "3.8800",
            "3. low": "3.7000",
            "4. close": "3.8400",
            "5. volume": "3759096"
        },
        "2023-12-05": {
            "1. open": "3.7300",
            "2. high": "3.7500",
            "3. low": "3.6100",
            "4. close": "3.7500",
            "5. volume": "3338644"
        },
        "2023-12-04": {
            "1. open": "3.8300",
            "2. high": "3.8700",
            "3. low": "3.7600",
            "4. close": "3.7700",
            "5. volume": "3270739"
        },
        "2023-12-01": {
            "1. open": "3.9500",
            "2. high": "3.9900",
            "3. low": "3.8900",
            "4. close": "3.8900",
            "5. volume": "2363599"
        },
        "2023-11-30": {
            "1. open": "3.9900",
            "2. high": "4.0200",
            "3. low": "3.9300",
            "4. close": "3.9700",
            "5. volume": "3532615"
        },
        "2023-11-29": {
            "1. open": "3.9900",
            "2. high": "4.0600",
            "3. low": "3.9900",
            "4. close": "4.0000",
            "5. volume": "6118809"
        },
        "2023-11-28": {
            "1. open": "3.8900",
            "2. high": "4.0400",
            "3. low": "3.8500",
            "4. close": "4.0100",
            "5. volume": "3850885"
        },
        "2023-11-27": {
            "1. open": "3.9300",
            "2. high": "3.9800",
            "3. low": "3.8700",
            "4. close": "3.9000",
            "5. volume": "5136866"
        },
        "2023-11-24": {
            "1. open": "3.9950",
            "2. high": "4.0300",
            "3. low": "3.9600",
            "4. close": "3.9800",
            "5. volume": "2306909"
        },
        "2023-11-22": {
            "1. open": "4.0500",
            "2. high": "4.0800",
            "3. low": "3.9800",
            "4. close": "4.0100",
            "5. volume": "4147382"
        },
        "2023-11-21": {
            "1. open": "4.0200",
            "2. high": "4.0800",
            "3. low": "4.0000",
            "4. close": "4.0500",
            "5. volume": "4113188"
        },
        "2023-11-20": {
            "1. open": "3.8400",
            "2. high": "4.0400",
            "3. low": "3.8200",
            "4. close": "4.0000",
            "5. volume": "4894628"
        },
        "2023-11-17": {
            "1. open": "3.8000",
            "2. high": "3.9100",
            "3. low": "3.7900",
            "4. close": "3.8400",
            "5. volume": "2485320"
        },
        "2023-11-16": {
            "1. open": "3.7400",
            "2. high": "3.8800",
            "3. low": "3.7400",
            "4. close": "3.8000",
            "5. volume": "3464791"
        },
        "2023-11-15": {
            "1. open": "3.8300",
            "2. high": "3.9600",
            "3. low": "3.7600",
            "4. close": "3.9000",
            "5. volume": "5418729"
        },
        "2023-11-14": {
            "1. open": "3.8100",
            "2. high": "3.9000",
            "3. low": "3.6700",
            "4. close": "3.8300",
            "5. volume": "7785723"
        },
        "2023-11-13": {
            "1. open": "3.6100",
            "2. high": "3.8400",
            "3. low": "3.5200",
            "4. close": "3.8200",
            "5. volume": "10051594"
        },
        "2023-11-10": {
            "1. open": "3.4300",
            "2. high": "3.4900",
            "3. low": "3.4300",
            "4. close": "3.4900",
            "5. volume": "1360746"
        },
        "2023-11-09": {
            "1. open": "3.4200",
            "2. high": "3.4700",
            "3. low": "3.4100",
            "4. close": "3.4500",
            "5. volume": "1524750"
        },
        "2023-11-08": {
            "1. open": "3.4500",
            "2. high": "3.4900",
            "3. low": "3.4100",
            "4. close": "3.4200",
            "5. volume": "1566505"
        },
        "2023-11-07": {
            "1. open": "3.4400",
            "2. high": "3.4700",
            "3. low": "3.4100",
            "4. close": "3.4400",
            "5. volume": "1520155"
        },
        "2023-11-06": {
            "1. open": "3.5500",
            "2. high": "3.5750",
            "3. low": "3.4300",
            "4. close": "3.4500",
            "5. volume": "1969088"
        },
        "2023-11-03": {
            "1. open": "3.4200",
            "2. high": "3.5000",
            "3. low": "3.4200",
            "4. close": "3.5000",
            "5. volume": "2207174"
        },
        "2023-11-02": {
            "1. open": "3.4000",
            "2. high": "3.4300",
            "3. low": "3.3600",
            "4. close": "3.4000",
            "5. volume": "3175082"
        },
        "2023-11-01": {
            "1. open": "3.3800",
            "2. high": "3.4400",
            "3. low": "3.3600",
            "4. close": "3.4000",
            "5. volume": "4554087"
        },
        "2023-10-31": {
            "1. open": "3.4100",
            "2. high": "3.4900",
            "3. low": "3.3800",
            "4. close": "3.3900",
            "5. volume": "3586332"
        },
        "2023-10-30": {
            "1. open": "3.4500",
            "2. high": "3.5000",
            "3. low": "3.4100",
            "4. close": "3.4800",
            "5. volume": "2608188"
        },
        "2023-10-27": {
            "1. open": "3.4100",
            "2. high": "3.4800",
            "3. low": "3.3800",
            "4. close": "3.4500",
            "5. volume": "3721383"
        },
        "2023-10-26": {
            "1. open": "3.3000",
            "2. high": "3.4200",
            "3. low": "3.3000",
            "4. close": "3.3300",
            "5. volume": "3416432"
        },
        "2023-10-25": {
            "1. open": "3.3500",
            "2. high": "3.3900",
            "3. low": "3.2900",
            "4. close": "3.3100",
            "5. volume": "1476740"
        },
        "2023-10-24": {
            "1. open": "3.2800",
            "2. high": "3.4700",
            "3. low": "3.2700",
            "4. close": "3.3900",
            "5. volume": "3705588"
        },
        "2023-10-23": {
            "1. open": "3.2800",
            "2. high": "3.4000",
            "3. low": "3.2400",
            "4. close": "3.2700",
            "5. volume": "1953544"
        },
        "2023-10-20": {
            "1. open": "3.3800",
            "2. high": "3.3900",
            "3. low": "3.2475",
            "4. close": "3.2800",
            "5. volume": "3801173"
        },
        "2023-10-19": {
            "1. open": "3.4700",
            "2. high": "3.4800",
            "3. low": "3.3600",
            "4. close": "3.3700",
            "5. volume": "2899979"
        },
        "2023-10-18": {
            "1. open": "3.5500",
            "2. high": "3.5700",
            "3. low": "3.4600",
            "4. close": "3.4900",
            "5. volume": "1300299"
        },
        "2023-10-17": {
            "1. open": "3.5100",
            "2. high": "3.7000",
            "3. low": "3.5000",
            "4. close": "3.5700",
            "5. volume": "3304846"
        },
        "2023-10-16": {
            "1. open": "3.4800",
            "2. high": "3.6400",
            "3. low": "3.4200",
            "4. close": "3.5700",
            "5. volume": "3869008"
        },
        "2023-10-13": {
            "1. open": "3.6300",
            "2. high": "3.6500",
            "3. low": "3.3800",
            "4. close": "3.4700",
            "5. volume": "6528061"
        },
        "2023-10-12": {
            "1. open": "3.4100",
            "2. high": "3.5100",
            "3. low": "3.3500",
            "4. close": "3.3600",
            "5. volume": "2694954"
        },
        "2023-10-11": {
            "1. open": "3.4700",
            "2. high": "3.4900",
            "3. low": "3.3700",
            "4. close": "3.4000",
            "5. volume": "1914039"
        },
        "2023-10-10": {
            "1. open": "3.3500",
            "2. high": "3.5200",
            "3. low": "3.3500",
            "4. close": "3.4900",
            "5. volume": "3787288"
        },
        "2023-10-09": {
            "1. open": "3.3200",
            "2. high": "3.4700",
            "3. low": "3.3100",
            "4. close": "3.3800",
            "5. volume": "3214125"
        },
        "2023-10-06": {
            "1. open": "3.2100",
            "2. high": "3.3500",
            "3. low": "3.2100",
            "4. close": "3.3500",
            "5. volume": "2386416"
        },
        "2023-10-05": {
            "1. open": "3.1900",
            "2. high": "3.2900",
            "3. low": "3.1900",
            "4. close": "3.2600",
            "5. volume": "2722089"
        },
        "2023-10-04": {
            "1. open": "3.1600",
            "2. high": "3.2900",
            "3. low": "3.1600",
            "4. close": "3.2700",
            "5. volume": "2401122"
        },
        "2023-10-03": {
            "1. open": "3.1700",
            "2. high": "3.2200",
            "3. low": "3.1500",
            "4. close": "3.1950",
            "5. volume": "1604917"
        },
        "2023-10-02": {
            "1. open": "3.1700",
            "2. high": "3.2500",
            "3. low": "3.1600",
            "4. close": "3.2300",
            "5. volume": "2378796"
        },
        "2023-09-29": {
            "1. open": "3.1600",
            "2. high": "3.2700",
            "3. low": "3.1600",
            "4. close": "3.2300",
            "5. volume": "3051003"
        },
        "2023-09-28": {
            "1. open": "3.1700",
            "2. high": "3.1800",
            "3. low": "3.1100",
            "4. close": "3.1600",
            "5. volume": "1968780"
        },
        "2023-09-27": {
            "1. open": "3.1600",
            "2. high": "3.2300",
            "3. low": "3.1400",
            "4. close": "3.2000",
            "5. volume": "984108"
        },
        "2023-09-26": {
            "1. open": "3.2000",
            "2. high": "3.2900",
            "3. low": "3.1200",
            "4. close": "3.2000",
            "5. volume": "3846468"
        },
        "2023-09-25": {
            "1. open": "3.2000",
            "2. high": "3.2700",
            "3. low": "3.1200",
            "4. close": "3.2500",
            "5. volume": "7237159"
        },
        "2023-09-22": {
            "1. open": "3.2200",
            "2. high": "3.2500",
            "3. low": "3.1800",
            "4. close": "3.2400",
            "5. volume": "3433733"
        },
        "2023-09-21": {
            "1. open": "3.2300",
            "2. high": "3.2399",
            "3. low": "3.1300",
            "4. close": "3.1600",
            "5. volume": "5966611"
        },
        "2023-09-20": {
            "1. open": "3.2800",
            "2. high": "3.3300",
            "3. low": "3.2300",
            "4. close": "3.3000",
            "5. volume": "3064455"
        },
        "2023-09-19": {
            "1. open": "3.3300",
            "2. high": "3.3600",
            "3. low": "3.2800",
            "4. close": "3.3400",
            "5. volume": "2690638"
        },
        "2023-09-18": {
            "1. open": "3.3800",
            "2. high": "3.4300",
            "3. low": "3.3500",
            "4. close": "3.3600",
            "5. volume": "3760658"
        },
        "2023-09-15": {
            "1. open": "3.4100",
            "2. high": "3.4400",
            "3. low": "3.3800",
            "4. close": "3.4300",
            "5. volume": "1904324"
        },
        "2023-09-14": {
            "1. open": "3.4200",
            "2. high": "3.4600",
            "3. low": "3.4000",
            "4. close": "3.4500",
            "5. volume": "1810994"
        },
        "2023-09-13": {
            "1. open": "3.4500",
            "2. high": "3.4700",
            "3. low": "3.3400",
            "4. close": "3.4700",
            "5. volume": "4096500"
        },
        "2023-09-12": {
            "1. open": "3.5000",
            "2. high": "3.5400",
            "3. low": "3.4300",
            "4. close": "3.4700",
            "5. volume": "6205893"
        },
        "2023-09-11": {
            "1. open": "3.5700",
            "2. high": "3.6500",
            "3. low": "3.4600",
            "4. close": "3.5100",
            "5. volume": "9507782"
        },
        "2023-09-08": {
            "1. open": "3.5000",
            "2. high": "3.5700",
            "3. low": "3.4500",
            "4. close": "3.5000",
            "5. volume": "5547668"
        },
        "2023-09-07": {
            "1. open": "3.4300",
            "2. high": "3.5100",
            "3. low": "3.3500",
            "4. close": "3.5100",
            "5. volume": "6650139"
        },
        "2023-09-06": {
            "1. open": "3.4900",
            "2. high": "3.5800",
            "3. low": "3.4400",
            "4. close": "3.5100",
            "5. volume": "6270876"
        },
        "2023-09-05": {
            "1. open": "3.2400",
            "2. high": "3.5300",
            "3. low": "3.2300",
            "4. close": "3.5000",
            "5. volume": "6321637"
        },
        "2023-09-01": {
            "1. open": "3.3600",
            "2. high": "3.4800",
            "3. low": "3.3500",
            "4. close": "3.4200",
            "5. volume": "6632279"
        },
        "2023-08-31": {
            "1. open": "3.4100",
            "2. high": "3.4500",
            "3. low": "3.3800",
            "4. close": "3.4300",
            "5. volume": "4118011"
        },
        "2023-08-30": {
            "1. open": "3.2800",
            "2. high": "3.4400",
            "3. low": "3.2300",
            "4. close": "3.4200",
            "5. volume": "6731762"
        },
        "2023-08-29": {
            "1. open": "3.2800",
            "2. high": "3.4000",
            "3. low": "3.2500",
            "4. close": "3.4000",
            "5. volume": "5832093"
        },
        "2023-08-28": {
            "1. open": "3.2700",
            "2. high": "3.2900",
            "3. low": "3.2200",
            "4. close": "3.2700",
            "5. volume": "3664771"
        },
        "2023-08-25": {
            "1. open": "3.1600",
            "2. high": "3.2500",
            "3. low": "3.1500",
            "4. close": "3.1700",
            "5. volume": "3667342"
        },
        "2023-08-24": {
            "1. open": "3.2700",
            "2. high": "3.3200",
            "3. low": "3.1800",
            "4. close": "3.2400",
            "5. volume": "6303805"
        },
        "2023-08-23": {
            "1. open": "3.2300",
            "2. high": "3.2900",
            "3. low": "3.2000",
            "4. close": "3.2800",
            "5. volume": "5127741"
        },
        "2023-08-22": {
            "1. open": "3.2700",
            "2. high": "3.3100",
            "3. low": "3.1600",
            "4. close": "3.3000",
            "5. volume": "10703107"
        },
        "2023-08-21": {
            "1. open": "3.0600",
            "2. high": "3.3300",
            "3. low": "3.0600",
            "4. close": "3.3200",
            "5. volume": "7866292"
        },
        "2023-08-18": {
            "1. open": "3.0300",
            "2. high": "3.1400",
            "3. low": "3.0000",
            "4. close": "3.1000",
            "5. volume": "4283421"
        },
        "2023-08-17": {
            "1. open": "3.0200",
            "2. high": "3.1165",
            "3. low": "3.0000",
            "4. close": "3.1000",
            "5. volume": "5969836"
        },
        "2023-08-16": {
            "1. open": "3.0500",
            "2. high": "3.1400",
            "3. low": "2.9200",
            "4. close": "3.0100",
            "5. volume": "5192842"
        },
        "2023-08-15": {
            "1. open": "3.1400",
            "2. high": "3.1500",
            "3. low": "3.0200",
            "4. close": "3.0600",
            "5. volume": "3959424"
        },
        "2023-08-14": {
            "1. open": "3.1300",
            "2. high": "3.1900",
            "3. low": "3.1200",
            "4. close": "3.1600",
            "5. volume": "2171739"
        },
        "2023-08-11": {
            "1. open": "3.1900",
            "2. high": "3.2300",
            "3. low": "3.1100",
            "4. close": "3.2000",
            "5. volume": "4998171"
        },
        "2023-08-10": {
            "1. open": "3.2100",
            "2. high": "3.3500",
            "3. low": "3.2100",
            "4. close": "3.2300",
            "5. volume": "6334163"
        },
        "2023-08-09": {
            "1. open": "3.3000",
            "2. high": "3.3000",
            "3. low": "3.1800",
            "4. close": "3.2100",
            "5. volume": "5829012"
        },
        "2023-08-08": {
            "1. open": "3.3000",
            "2. high": "3.3300",
            "3. low": "3.2300",
            "4. close": "3.2700",
            "5. volume": "7267977"
        },
        "2023-08-07": {
            "1. open": "3.4400",
            "2. high": "3.4400",
            "3. low": "3.3300",
            "4. close": "3.3900",
            "5. volume": "4981325"
        },
        "2023-08-04": {
            "1. open": "3.5100",
            "2. high": "3.5500",
            "3. low": "3.4600",
            "4. close": "3.4800",
            "5. volume": "6254897"
        },
        "2023-08-03": {
            "1. open": "3.4800",
            "2. high": "3.6000",
            "3. low": "3.4500",
            "4. close": "3.5700",
            "5. volume": "11838691"
        },
        "2023-08-02": {
            "1. open": "3.4900",
            "2. high": "3.5000",
            "3. low": "3.3500",
            "4. close": "3.4700",
            "5. volume": "10302129"
        },
        "2023-08-01": {
            "1. open": "3.6700",
            "2. high": "3.7000",
            "3. low": "3.5000",
            "4. close": "3.6000",
            "5. volume": "8130294"
        },
        "2023-07-31": {
            "1. open": "3.7400",
            "2. high": "3.8400",
            "3. low": "3.5900",
            "4. close": "3.7600",
            "5. volume": "21984370"
        },
        "2023-07-28": {
            "1. open": "3.5000",
            "2. high": "3.8600",
            "3. low": "3.4800",
            "4. close": "3.8600",
            "5. volume": "26062807"
        },
        "2023-07-27": {
            "1. open": "3.4400",
            "2. high": "3.5000",
            "3. low": "3.3600",
            "4. close": "3.4500",
            "5. volume": "9952960"
        },
        "2023-07-26": {
            "1. open": "3.3100",
            "2. high": "3.4900",
            "3. low": "3.2800",
            "4. close": "3.4400",
            "5. volume": "13035791"
        },
        "2023-07-25": {
            "1. open": "3.2700",
            "2. high": "3.3900",
            "3. low": "3.2600",
            "4. close": "3.3700",
            "5. volume": "12909730"
        },
        "2023-07-24": {
            "1. open": "3.0200",
            "2. high": "3.3000",
            "3. low": "3.0200",
            "4. close": "3.2200",
            "5. volume": "7075278"
        },
        "2023-07-21": {
            "1. open": "3.1000",
            "2. high": "3.1400",
            "3. low": "2.9750",
            "4. close": "3.0300",
            "5. volume": "4870940"
        },
        "2023-07-20": {
            "1. open": "3.1300",
            "2. high": "3.1500",
            "3. low": "3.0400",
            "4. close": "3.0800",
            "5. volume": "4269604"
        },
        "2023-07-19": {
            "1. open": "3.0600",
            "2. high": "3.1700",
            "3. low": "3.0600",
            "4. close": "3.1500",
            "5. volume": "6980402"
        },
        "2023-07-18": {
            "1. open": "3.1400",
            "2. high": "3.1800",
            "3. low": "3.0000",
            "4. close": "3.0200",
            "5. volume": "3923449"
        },
        "2023-07-17": {
            "1. open": "3.1000",
            "2. high": "3.2000",
            "3. low": "3.0800",
            "4. close": "3.1900",
            "5. volume": "2410051"
        },
        "2023-07-14": {
            "1. open": "3.2200",
            "2. high": "3.2300",
            "3. low": "3.0600",
            "4. close": "3.0800",
            "5. volume": "4524683"
        },
        "2023-07-13": {
            "1. open": "3.3800",
            "2. high": "3.4100",
            "3. low": "3.2300",
            "4. close": "3.2300",
            "5. volume": "14025688"
        },
        "2023-07-12": {
            "1. open": "3.5250",
            "2. high": "3.5700",
            "3. low": "3.2500",
            "4. close": "3.3400",
            "5. volume": "11064802"
        },
        "2023-07-11": {
            "1. open": "3.3700",
            "2. high": "3.5700",
            "3. low": "3.3400",
            "4. close": "3.4700",
            "5. volume": "13220369"
        },
        "2023-07-10": {
            "1. open": "3.0900",
            "2. high": "3.3900",
            "3. low": "3.0600",
            "4. close": "3.3100",
            "5. volume": "17635640"
        },
        "2023-07-07": {
            "1. open": "2.9900",
            "2. high": "3.0300",
            "3. low": "2.9700",
            "4. close": "3.0000",
            "5. volume": "11579716"
        },
        "2023-07-06": {
            "1. open": "2.9800",
            "2. high": "3.0100",
            "3. low": "2.9500",
            "4. close": "2.9800",
            "5. volume": "7415844"
        },
        "2023-07-05": {
            "1. open": "2.9600",
            "2. high": "3.0100",
            "3. low": "2.9300",
            "4. close": "3.0000",
            "5. volume": "11197388"
        },
        "2023-07-03": {
            "1. open": "3.0000",
            "2. high": "3.0100",
            "3. low": "2.9800",
            "4. close": "3.0000",
            "5. volume": "5393222"
        },
        "2023-06-30": {
            "1. open": "2.9700",
            "2. high": "3.0100",
            "3. low": "2.9500",
            "4. close": "3.0000",
            "5. volume": "3895434"
        },
        "2023-06-29": {
            "1. open": "2.9600",
            "2. high": "3.0100",
            "3. low": "2.9300",
            "4. close": "3.0000",
            "5. volume": "3870327"
        },
        "2023-06-28": {
            "1. open": "2.9400",
            "2. high": "3.0100",
            "3. low": "2.8900",
            "4. close": "3.0000",
            "5. volume": "4889786"
        },
        "2023-06-27": {
            "1. open": "2.9100",
            "2. high": "3.0300",
            "3. low": "2.9000",
            "4. close": "2.9900",
            "5. volume": "5888829"
        },
        "2023-06-26": {
            "1. open": "2.7700",
            "2. high": "2.9700",
            "3. low": "2.7600",
            "4. close": "2.9500",
            "5. volume": "4654452"
        },
        "2023-06-23": {
            "1. open": "2.8400",
            "2. high": "2.8900",
            "3. low": "2.7700",
            "4. close": "2.7700",
            "5. volume": "3248438"
        },
        "2023-06-22": {
            "1. open": "2.9000",
            "2. high": "2.9100",
            "3. low": "2.8100",
            "4. close": "2.8800",
            "5. volume": "2894731"
        },
        "2023-06-21": {
            "1. open": "2.8700",
            "2. high": "2.9200",
            "3. low": "2.8600",
            "4. close": "2.9200",
            "5. volume": "3008918"
        },
        "2023-06-20": {
            "1. open": "2.8500",
            "2. high": "2.9700",
            "3. low": "2.8000",
            "4. close": "2.9600",
            "5. volume": "5794669"
        },
        "2023-06-16": {
            "1. open": "3.0000",
            "2. high": "3.0200",
            "3. low": "2.9500",
            "4. close": "2.9700",
            "5. volume": "5314697"
        },
        "2023-06-15": {
            "1. open": "2.9300",
            "2. high": "3.0300",
            "3. low": "2.9100",
            "4. close": "3.0000",
            "5. volume": "14653817"
        },
        "2023-06-14": {
            "1. open": "2.9500",
            "2. high": "2.9500",
            "3. low": "2.8200",
            "4. close": "2.8800",
            "5. volume": "6545204"
        },
        "2023-06-13": {
            "1. open": "3.0000",
            "2. high": "3.0500",
            "3. low": "2.9400",
            "4. close": "2.9700",
            "5. volume": "5897894"
        },
        "2023-06-12": {
            "1. open": "2.9400",
            "2. high": "2.9600",
            "3. low": "2.9100",
            "4. close": "2.9500",
            "5. volume": "2170718"
        },
        "2023-06-09": {
            "1. open": "2.9000",
            "2. high": "2.9800",
            "3. low": "2.9000",
            "4. close": "2.9500",
            "5. volume": "7109945"
        },
        "2023-06-08": {
            "1. open": "2.8900",
            "2. high": "2.9500",
            "3. low": "2.8200",
            "4. close": "2.9500",
            "5. volume": "5444219"
        },
        "2023-06-07": {
            "1. open": "2.8650",
            "2. high": "2.9650",
            "3. low": "2.8500",
            "4. close": "2.8900",
            "5. volume": "2931418"
        },
        "2023-06-06": {
            "1. open": "2.8500",
            "2. high": "3.0200",
            "3. low": "2.8300",
            "4. close": "2.9700",
            "5. volume": "4462146"
        },
        "2023-06-05": {
            "1. open": "2.7700",
            "2. high": "2.9300",
            "3. low": "2.7500",
            "4. close": "2.9100",
            "5. volume": "3057607"
        },
        "2023-06-02": {
            "1. open": "2.9300",
            "2. high": "2.9800",
            "3. low": "2.7600",
            "4. close": "2.7900",
            "5. volume": "5836307"
        },
        "2023-06-01": {
            "1. open": "2.5100",
            "2. high": "2.8500",
            "3. low": "2.5100",
            "4. close": "2.8400",
            "5. volume": "8836262"
        },
        "2023-05-31": {
            "1. open": "2.5400",
            "2. high": "2.5700",
            "3. low": "2.4800",
            "4. close": "2.5600",
            "5. volume": "11402969"
        },
        "2023-05-30": {
            "1. open": "2.6200",
            "2. high": "2.7500",
            "3. low": "2.4800",
            "4. close": "2.5000",
            "5. volume": "18902854"
        },
        "2023-05-26": {
            "1. open": "2.7200",
            "2. high": "2.8400",
            "3. low": "2.6400",
            "4. close": "2.6400",
            "5. volume": "9207707"
        },
        "2023-05-25": {
            "1. open": "2.7700",
            "2. high": "2.7800",
            "3. low": "2.6100",
            "4. close": "2.6600",
            "5. volume": "15586447"
        },
        "2023-05-24": {
            "1. open": "2.9500",
            "2. high": "2.9600",
            "3. low": "2.7800",
            "4. close": "2.7900",
            "5. volume": "21019700"
        },
        "2023-05-23": {
            "1. open": "3.0300",
            "2. high": "3.0700",
            "3. low": "2.9600",
            "4. close": "2.9900",
            "5. volume": "5556781"
        },
        "2023-05-22": {
            "1. open": "3.1500",
            "2. high": "3.1900",
            "3. low": "3.0100",
            "4. close": "3.0300",
            "5. volume": "5026807"
        },
        "2023-05-19": {
            "1. open": "3.1900",
            "2. high": "3.1900",
            "3. low": "3.0000",
            "4. close": "3.0900",
            "5. volume": "11171828"
        },
        "2023-05-18": {
            "1. open": "3.2503",
            "2. high": "3.2800",
            "3. low": "3.0900",
            "4. close": "3.1900",
            "5. volume": "9748493"
        },
        "2023-05-17": {
            "1. open": "3.2200",
            "2. high": "3.3000",
            "3. low": "3.1600",
            "4. close": "3.3000",
            "5. volume": "6698025"
        },
        "2023-05-16": {
            "1. open": "3.2100",
            "2. high": "3.2700",
            "3. low": "3.2000",
            "4. close": "3.2100",
            "5. volume": "2222399"
        },
        "2023-05-15": {
            "1. open": "3.2000",
            "2. high": "3.3400",
            "3. low": "3.1900",
            "4. close": "3.2600",
            "5. volume": "2650220"
        },
        "2023-05-12": {
            "1. open": "3.2800",
            "2. high": "3.3000",
            "3. low": "3.1600",
            "4. close": "3.2600",
            "5. volume": "4825370"
        },
        "2023-05-11": {
            "1. open": "3.3500",
            "2. high": "3.3700",
            "3. low": "3.2600",
            "4. close": "3.3500",
            "5. volume": "4584191"
        },
        "2023-05-10": {
            "1. open": "3.3000",
            "2. high": "3.4100",
            "3. low": "3.1000",
            "4. close": "3.4100",
            "5. volume": "15017408"
        },
        "2023-05-09": {
            "1. open": "3.4500",
            "2. high": "3.4500",
            "3. low": "3.2500",
            "4. close": "3.3100",
            "5. volume": "4661517"
        },
        "2023-05-08": {
            "1. open": "3.5000",
            "2. high": "3.5100",
            "3. low": "3.4200",
            "4. close": "3.5000",
            "5. volume": "3718232"
        },
        "2023-05-05": {
            "1. open": "3.4100",
            "2. high": "3.5000",
            "3. low": "3.3600",
            "4. close": "3.5000",
            "5. volume": "4605242"
        },
        "2023-05-04": {
            "1. open": "3.4400",
            "2. high": "3.5100",
            "3. low": "3.3800",
            "4. close": "3.4300",
            "5. volume": "5843524"
        },
        "2023-05-03": {
            "1. open": "3.6000",
            "2. high": "3.6800",
            "3. low": "3.4600",
            "4. close": "3.5200",
            "5. volume": "2272764"
        },
        "2023-05-02": {
            "1. open": "3.7800",
            "2. high": "3.8000",
            "3. low": "3.5500",
            "4. close": "3.6000",
            "5. volume": "3918396"
        },
        "2023-05-01": {
            "1. open": "3.8600",
            "2. high": "3.9000",
            "3. low": "3.7600",
            "4. close": "3.8700",
            "5. volume": "3371410"
        },
        "2023-04-28": {
            "1. open": "3.5200",
            "2. high": "3.8000",
            "3. low": "3.4600",
            "4. close": "3.8000",
            "5. volume": "5548625"
        },
        "2023-04-27": {
            "1. open": "3.2300",
            "2. high": "3.6500",
            "3. low": "3.1800",
            "4. close": "3.6500",
            "5. volume": "11162479"
        },
        "2023-04-26": {
            "1. open": "3.2200",
            "2. high": "3.3000",
            "3. low": "3.1700",
            "4. close": "3.2700",
            "5. volume": "2890047"
        },
        "2023-04-25": {
            "1. open": "3.1400",
            "2. high": "3.2025",
            "3. low": "2.9600",
            "4. close": "3.1900",
            "5. volume": "11089278"
        },
        "2023-04-24": {
            "1. open": "3.4000",
            "2. high": "3.4700",
            "3. low": "3.2100",
            "4. close": "3.2200",
            "5. volume": "11780449"
        },
        "2023-04-21": {
            "1. open": "3.4400",
            "2. high": "3.6100",
            "3. low": "3.4200",
            "4. close": "3.4500",
            "5. volume": "4188095"
        },
        "2023-04-20": {
            "1. open": "3.4150",
            "2. high": "3.5700",
            "3. low": "3.3800",
            "4. close": "3.4900",
            "5. volume": "4343948"
        },
        "2023-04-19": {
            "1. open": "3.4430",
            "2. high": "3.4500",
            "3. low": "3.3800",
            "4. close": "3.4200",
            "5. volume": "3556036"
        },
        "2023-04-18": {
            "1. open": "3.5500",
            "2. high": "3.5900",
            "3. low": "3.3700",
            "4. close": "3.4300",
            "5. volume": "14483476"
        },
        "2023-04-17": {
            "1. open": "3.5700",
            "2. high": "3.7500",
            "3. low": "3.4400",
            "4. close": "3.4900",
            "5. volume": "9545068"
        },
        "2023-04-14": {
            "1. open": "3.6500",
            "2. high": "3.7500",
            "3. low": "3.5800",
            "4. close": "3.6100",
            "5. volume": "3184544"
        },
        "2023-04-13": {
            "1. open": "3.6600",
            "2. high": "3.8200",
            "3. low": "3.6100",
            "4. close": "3.6300",
            "5. volume": "8366398"
        },
        "2023-04-12": {
            "1. open": "3.7600",
            "2. high": "3.7900",
            "3. low": "3.6200",
            "4. close": "3.6600",
            "5. volume": "6101470"
        },
        "2023-04-11": {
            "1. open": "3.8303",
            "2. high": "3.8400",
            "3. low": "3.7500",
            "4. close": "3.7500",
            "5. volume": "8386143"
        },
        "2023-04-10": {
            "1. open": "3.8000",
            "2. high": "3.8500",
            "3. low": "3.7500",
            "4. close": "3.8400",
            "5. volume": "1982348"
        },
        "2023-04-06": {
            "1. open": "3.7000",
            "2. high": "3.9300",
            "3. low": "3.6900",
            "4. close": "3.8900",
            "5. volume": "3219937"
        },
        "2023-04-05": {
            "1. open": "3.7100",
            "2. high": "3.7500",
            "3. low": "3.6500",
            "4. close": "3.7000",
            "5. volume": "6642813"
        },
        "2023-04-04": {
            "1. open": "3.8000",
            "2. high": "3.8300",
            "3. low": "3.6700",
            "4. close": "3.7000",
            "5. volume": "4115487"
        },
        "2023-04-03": {
            "1. open": "3.7700",
            "2. high": "3.8800",
            "3. low": "3.7600",
            "4. close": "3.8200",
            "5. volume": "5551233"
        },
        "2023-03-31": {
            "1. open": "3.9300",
            "2. high": "3.9500",
            "3. low": "3.7800",
            "4. close": "3.8000",
            "5. volume": "10453823"
        },
        "2023-03-30": {
            "1. open": "3.9800",
            "2. high": "3.9900",
            "3. low": "3.8200",
            "4. close": "3.9500",
            "5. volume": "16764661"
        },
        "2023-03-29": {
            "1. open": "3.9700",
            "2. high": "4.0400",
            "3. low": "3.9200",
            "4. close": "3.9700",
            "5. volume": "7652929"
        },
        "2023-03-28": {
            "1. open": "3.9100",
            "2. high": "3.9900",
            "3. low": "3.8300",
            "4. close": "3.9800",
            "5. volume": "7462919"
        },
        "2023-03-27": {
            "1. open": "3.6300",
            "2. high": "3.7900",
            "3. low": "3.5700",
            "4. close": "3.7600",
            "5. volume": "6809287"
        },
        "2023-03-24": {
            "1. open": "3.6800",
            "2. high": "3.6900",
            "3. low": "3.5150",
            "4. close": "3.6500",
            "5. volume": "3503086"
        },
        "2023-03-23": {
            "1. open": "3.7500",
            "2. high": "3.8500",
            "3. low": "3.7000",
            "4. close": "3.7100",
            "5. volume": "6707119"
        },
        "2023-03-22": {
            "1. open": "3.6200",
            "2. high": "3.7200",
            "3. low": "3.5100",
            "4. close": "3.6500",
            "5. volume": "3742709"
        },
        "2023-03-21": {
            "1. open": "3.5400",
            "2. high": "3.6800",
            "3. low": "3.4400",
            "4. close": "3.6500",
            "5. volume": "8933420"
        },
        "2023-03-20": {
            "1. open": "3.4800",
            "2. high": "3.4800",
            "3. low": "3.3100",
            "4. close": "3.4300",
            "5. volume": "5174087"
        },
        "2023-03-17": {
            "1. open": "3.6400",
            "2. high": "3.6800",
            "3. low": "3.4100",
            "4. close": "3.5100",
            "5. volume": "5554144"
        },
        "2023-03-16": {
            "1. open": "3.5100",
            "2. high": "3.6100",
            "3. low": "3.4100",
            "4. close": "3.6000",
            "5. volume": "9611776"
        },
        "2023-03-15": {
            "1. open": "3.7000",
            "2. high": "3.7000",
            "3. low": "3.2400",
            "4. close": "3.6300",
            "5. volume": "29715519"
        },
        "2023-03-14": {
            "1. open": "3.9700",
            "2. high": "4.5000",
            "3. low": "3.6300",
            "4. close": "3.7300",
            "5. volume": "17966139"
        },
        "2023-03-13": {
            "1. open": "3.9000",
            "2. high": "4.1100",
            "3. low": "3.6700",
            "4. close": "4.0100",
            "5. volume": "10456810"
        },
        "2023-03-10": {
            "1. open": "4.0500",
            "2. high": "4.1000",
            "3. low": "3.8600",
            "4. close": "3.9200",
            "5. volume": "16217039"
        },
        "2023-03-09": {
            "1. open": "4.2000",
            "2. high": "4.2800",
            "3. low": "4.0600",
            "4. close": "4.1700",
            "5. volume": "8024136"
        },
        "2023-03-08": {
            "1. open": "4.1100",
            "2. high": "4.3900",
            "3. low": "4.0700",
            "4. close": "4.3200",
            "5. volume": "6824328"
        },
        "2023-03-07": {
            "1. open": "4.2900",
            "2. high": "4.4000",
            "3. low": "4.0300",
            "4. close": "4.0700",
            "5. volume": "8546360"
        },
        "2023-03-06": {
            "1. open": "4.3400",
            "2. high": "4.5000",
            "3. low": "4.2100",
            "4. close": "4.3600",
            "5. volume": "5936211"
        },
        "2023-03-03": {
            "1. open": "4.1400",
            "2. high": "4.3800",
            "3. low": "4.0100",
            "4. close": "4.3500",
            "5. volume": "11439410"
        },
        "2023-03-02": {
            "1. open": "3.9600",
            "2. high": "4.1200",
            "3. low": "3.9000",
            "4. close": "4.1200",
            "5. volume": "8441848"
        },
        "2023-03-01": {
            "1. open": "4.0900",
            "2. high": "4.1700",
            "3. low": "4.0000",
            "4. close": "4.0800",
            "5. volume": "8267370"
        },
        "2023-02-28": {
            "1. open": "4.1000",
            "2. high": "4.1000",
            "3. low": "3.6200",
            "4. close": "3.9800",
            "5. volume": "19298267"
        },
        "2023-02-27": {
            "1. open": "4.1300",
            "2. high": "4.1900",
            "3. low": "4.0800",
            "4. close": "4.1200",
            "5. volume": "4239432"
        },
        "2023-02-24": {
            "1. open": "4.3400",
            "2. high": "4.3700",
            "3. low": "4.0200",
            "4. close": "4.0300",
            "5. volume": "8870821"
        },
        "2023-02-23": {
            "1. open": "4.3900",
            "2. high": "4.5200",
            "3. low": "4.3300",
            "4. close": "4.4700",
            "5. volume": "5419186"
        },
        "2023-02-22": {
            "1. open": "4.4800",
            "2. high": "4.5700",
            "3. low": "4.3900",
            "4. close": "4.4900",
            "5. volume": "5684502"
        },
        "2023-02-21": {
            "1. open": "4.4700",
            "2. high": "4.4900",
            "3. low": "4.4000",
            "4. close": "4.4900",
            "5. volume": "11484613"
        },
        "2023-02-17": {
            "1. open": "4.4800",
            "2. high": "4.6800",
            "3. low": "4.3600",
            "4. close": "4.5100",
            "5. volume": "7521875"
        },
        "2023-02-16": {
            "1. open": "4.3100",
            "2. high": "4.6100",
            "3. low": "4.3100",
            "4. close": "4.5900",
            "5. volume": "13833079"
        },
        "2023-02-15": {
            "1. open": "4.3600",
            "2. high": "4.3900",
            "3. low": "4.3100",
            "4. close": "4.3900",
            "5. volume": "6066756"
        },
        "2023-02-14": {
            "1. open": "4.3400",
            "2. high": "4.4000",
            "3. low": "4.2900",
            "4. close": "4.3900",
            "5. volume": "8519701"
        },
        "2023-02-13": {
            "1. open": "4.3000",
            "2. high": "4.4000",
            "3. low": "4.2800",
            "4. close": "4.3500",
            "5. volume": "6420258"
        },
        "2023-02-10": {
            "1. open": "4.3400",
            "2. high": "4.3700",
            "3. low": "0.2800",
            "4. close": "4.2600",
            "5. volume": "11654915"
        },
        "2023-02-09": {
            "1. open": "4.4000",
            "2. high": "4.4700",
            "3. low": "4.3700",
            "4. close": "4.4200",
            "5. volume": "10562606"
        },
        "2023-02-08": {
            "1. open": "4.3500",
            "2. high": "4.4900",
            "3. low": "4.2600",
            "4. close": "4.3500",
            "5. volume": "7862343"
        },
        "2023-02-07": {
            "1. open": "4.3300",
            "2. high": "4.5000",
            "3. low": "4.2800",
            "4. close": "4.4700",
            "5. volume": "7251798"
        },
        "2023-02-06": {
            "1. open": "4.3600",
            "2. high": "4.3700",
            "3. low": "4.1800",
            "4. close": "4.3100",
            "5. volume": "6864718"
        },
        "2023-02-03": {
            "1. open": "4.5600",
            "2. high": "4.5800",
            "3. low": "4.3700",
            "4. close": "4.4200",
            "5. volume": "10978446"
        },
        "2023-02-02": {
            "1. open": "4.6500",
            "2. high": "4.6600",
            "3. low": "4.4300",
            "4. close": "4.5900",
            "5. volume": "19696669"
        },
        "2023-02-01": {
            "1. open": "4.6100",
            "2. high": "4.7200",
            "3. low": "4.4300",
            "4. close": "4.5900",
            "5. volume": "6312734"
        },
        "2023-01-31": {
            "1. open": "4.3100",
            "2. high": "4.6800",
            "3. low": "4.2300",
            "4. close": "4.5200",
            "5. volume": "11901479"
        },
        "2023-01-30": {
            "1. open": "4.1500",
            "2. high": "4.3100",
            "3. low": "4.1500",
            "4. close": "4.2600",
            "5. volume": "11666632"
        },
        "2023-01-27": {
            "1. open": "4.3500",
            "2. high": "4.4300",
            "3. low": "4.2200",
            "4. close": "4.2800",
            "5. volume": "12512412"
        },
        "2023-01-26": {
            "1. open": "4.4500",
            "2. high": "4.5400",
            "3. low": "4.3100",
            "4. close": "4.3100",
            "5. volume": "9989895"
        },
        "2023-01-25": {
            "1. open": "4.4100",
            "2. high": "4.4700",
            "3. low": "4.2500",
            "4. close": "4.3000",
            "5. volume": "9920242"
        },
        "2023-01-24": {
            "1. open": "4.6200",
            "2. high": "4.6300",
            "3. low": "4.4000",
            "4. close": "4.4000",
            "5. volume": "6009363"
        },
        "2023-01-23": {
            "1. open": "4.8200",
            "2. high": "4.8700",
            "3. low": "4.5600",
            "4. close": "4.6000",
            "5. volume": "12159038"
        },
        "2023-01-20": {
            "1. open": "4.5900",
            "2. high": "4.8900",
            "3. low": "4.5300",
            "4. close": "4.8300",
            "5. volume": "19425819"
        },
        "2023-01-19": {
            "1. open": "4.3100",
            "2. high": "4.6200",
            "3. low": "4.2700",
            "4. close": "4.4400",
            "5. volume": "23002671"
        },
        "2023-01-18": {
            "1. open": "4.2100",
            "2. high": "4.4800",
            "3. low": "4.0100",
            "4. close": "4.1400",
            "5. volume": "41671680"
        },
        "2023-01-17": {
            "1. open": "4.9900",
            "2. high": "4.9900",
            "3. low": "4.6000",
            "4. close": "4.6900",
            "5. volume": "29817796"
        },
        "2023-01-13": {
            "1. open": "4.9650",
            "2. high": "4.9900",
            "3. low": "4.5500",
            "4. close": "4.6000",
            "5. volume": "54835923"
        },
        "2023-01-12": {
            "1. open": "4.7000",
            "2. high": "4.8500",
            "3. low": "4.6100",
            "4. close": "4.6300",
            "5. volume": "22538347"
        },
        "2023-01-11": {
            "1. open": "4.5600",
            "2. high": "4.8900",
            "3. low": "4.5200",
            "4. close": "4.7000",
            "5. volume": "19125224"
        },
        "2023-01-10": {
            "1. open": "4.5500",
            "2. high": "4.7000",
            "3. low": "4.4700",
            "4. close": "4.5100",
            "5. volume": "10841683"
        },
        "2023-01-09": {
            "1. open": "4.9400",
            "2. high": "5.0500",
            "3. low": "4.3800",
            "4. close": "4.4200",
            "5. volume": "33311640"
        },
        "2023-01-06": {
            "1. open": "4.0800",
            "2. high": "4.9500",
            "3. low": "4.0200",
            "4. close": "4.6800",
            "5. volume": "46339322"
        },
        "2023-01-05": {
            "1. open": "3.8800",
            "2. high": "4.1500",
            "3. low": "3.7800",
            "4. close": "4.1000",
            "5. volume": "18257095"
        },
        "2023-01-04": {
            "1. open": "3.7500",
            "2. high": "3.9900",
            "3. low": "3.7100",
            "4. close": "3.9800",
            "5. volume": "24121606"
        },
        "2023-01-03": {
            "1. open": "3.3900",
            "2. high": "3.5700",
            "3. low": "3.3300",
            "4. close": "3.5400",
            "5. volume": "13232983"
        },
        "2022-12-30": {
            "1. open": "3.1000",
            "2. high": "3.2300",
            "3. low": "3.0900",
            "4. close": "3.1800",
            "5. volume": "8760318"
        },
        "2022-12-29": {
            "1. open": "3.1900",
            "2. high": "3.4200",
            "3. low": "3.1500",
            "4. close": "3.3400",
            "5. volume": "10176057"
        },
        "2022-12-28": {
            "1. open": "3.4400",
            "2. high": "3.4500",
            "3. low": "3.0700",
            "4. close": "3.2000",
            "5. volume": "12077253"
        },
        "2022-12-27": {
            "1. open": "3.6300",
            "2. high": "3.7100",
            "3. low": "3.3700",
            "4. close": "3.4600",
            "5. volume": "6478870"
        },
        "2022-12-23": {
            "1. open": "3.7000",
            "2. high": "3.8100",
            "3. low": "3.6100",
            "4. close": "3.6700",
            "5. volume": "8406069"
        },
        "2022-06-13": {
            "1. open": "2.2000",
            "2. high": "2.5400",
            "3. low": "2.1100",
            "4. close": "2.4600",
            "5. volume": "24482674"
        }
    }
}