{
    "Symbol": "AVY",
    "AssetType": "Common Stock",
    "Name": "Avery Dennison Corp",
    "Description": "Avery Dennison Corporation is a multinational manufacturer and distributor of pressure-sensitive adhesive materials (such as self-adhesive labels), apparel branding labels and tags, RFID inlays, and specialty medical products. The company is headquartered in Glendale, California.",
    "CIK": "8818",
    "Exchange": "NYSE",
    "Currency": "USD",
    "Country": "USA",
    "Sector": "MANUFACTURING",
    "Industry": "CONVERTED PAPER & PAPERBOARD PRODS (NO CONTANERS/BOXES)",
    "Address": "207 GOODE AVENUE, GLENDALE, CA, US",
    "FiscalYearEnd": "December",
    "LatestQuarter": "2024-06-30",
    "MarketCapitalization": "16939609000",
    "EBITDA": "1394600000",
    "PERatio": "27.08",
    "PEGRatio": "1.435",
    "BookValue": "28.39",
    "DividendPerShare": "3.31",
    "DividendYield": "0.0164",
    "EPS": "7.77",
    "RevenuePerShareTTM": "106.71",
    "ProfitMargin": "0.0734",
    "OperatingMarginTTM": "0.129",
    "ReturnOnAssetsTTM": "0.0838",
    "ReturnOnEquityTTM": "0.293",
    "RevenueTTM": "8595400000",
    "GrossProfitTTM": "2404200000",
    "DilutedEPSTTM": "7.77",
    "QuarterlyEarningsGrowthYOY": "0.758",
    "QuarterlyRevenueGrowthYOY": "0.069",
    "AnalystTargetPrice": "241.83",
    "AnalystRatingStrongBuy": "2",
    "AnalystRatingBuy": "7",
    "AnalystRatingHold": "3",
    "AnalystRatingSell": "1",
    "AnalystRatingStrongSell": "0",
    "TrailingPE": "27.08",
    "ForwardPE": "22.37",
    "PriceToSalesRatioTTM": "1.971",
    "PriceToBookRatio": "7.41",
    "EVToRevenue": "2.321",
    "EVToEBITDA": "15.52",
    "Beta": "0.89",
    "52WeekHigh": "233.47",
    "52WeekLow": "163.28",
    "50DayMovingAverage": "222.09",
    "200DayMovingAverage": "207.85",
    "SharesOutstanding": "80519000",
    "DividendDate": "2024-09-18",
    "ExDividendDate": "2024-09-04"
}