{
    "Symbol": "AXON",
    "AssetType": "Common Stock",
    "Name": "Axon Enterprise Inc.",
    "Description": "Axon Enterprise, Inc. develops, manufactures, and sells conducted energy weapons (DEC) under the TASER brand name in the United States and internationally. The company is headquartered in Scottsdale, Arizona.",
    "CIK": "1069183",
    "Exchange": "NASDAQ",
    "Currency": "USD",
    "Country": "USA",
    "Sector": "MANUFACTURING",
    "Industry": "ORDNANCE & ACCESSORIES, (NO VEHICLES/GUIDED MISSILES)",
    "Address": "17800 N. 85TH ST., SCOTTSDALE, AZ, US",
    "FiscalYearEnd": "December",
    "LatestQuarter": "2024-03-31",
    "MarketCapitalization": "22163585000",
    "EBITDA": "194274000",
    "PERatio": "85.87",
    "PEGRatio": "2.86",
    "BookValue": "24.09",
    "DividendPerShare": "None",
    "DividendYield": "None",
    "EPS": "3.42",
    "RevenuePerShareTTM": "22.45",
    "ProfitMargin": "0.156",
    "OperatingMarginTTM": "0.0353",
    "ReturnOnAssetsTTM": "0.0296",
    "ReturnOnEquityTTM": "0.163",
    "RevenueTTM": "1681084000",
    "GrossProfitTTM": "728638000",
    "DilutedEPSTTM": "3.42",
    "QuarterlyEarningsGrowthYOY": "1.836",
    "QuarterlyRevenueGrowthYOY": "0.343",
    "AnalystTargetPrice": "360.12",
    "AnalystRatingStrongBuy": "4",
    "AnalystRatingBuy": "8",
    "AnalystRatingHold": "2",
    "AnalystRatingSell": "0",
    "AnalystRatingStrongSell": "0",
    "TrailingPE": "85.87",
    "ForwardPE": "68.03",
    "PriceToSalesRatioTTM": "15.0",
    "PriceToBookRatio": "14.55",
    "EVToRevenue": "14.61",
    "EVToEBITDA": "117.35",
    "Beta": "0.952",
    "52WeekHigh": "329.87",
    "52WeekLow": "175.59",
    "50DayMovingAverage": "295.4",
    "200DayMovingAverage": "274.48",
    "SharesOutstanding": "75467000",
    "DividendDate": "None",
    "ExDividendDate": "None"
}