{
    "Symbol": "COP",
    "AssetType": "Common Stock",
    "Name": "ConocoPhillips",
    "Description": "ConocoPhillips is an American multinational corporation engaged in hydrocarbon exploration. It is based in the Energy Corridor district of Houston, Texas.",
    "CIK": "1163165",
    "Exchange": "NYSE",
    "Currency": "USD",
    "Country": "USA",
    "Sector": "ENERGY & TRANSPORTATION",
    "Industry": "PETROLEUM REFINING",
    "Address": "925 N. ELDRIDGE PARKWAY, HOUSTON, TX, US",
    "FiscalYearEnd": "December",
    "LatestQuarter": "2024-03-31",
    "MarketCapitalization": "123149066000",
    "EBITDA": "24996999000",
    "PERatio": "11.98",
    "PEGRatio": "0.721",
    "BookValue": "42.84",
    "DividendPerShare": "3.85",
    "DividendYield": "0.03",
    "EPS": "8.83",
    "RevenuePerShareTTM": "49.11",
    "ProfitMargin": "0.184",
    "OperatingMarginTTM": "0.27",
    "ReturnOnAssetsTTM": "0.109",
    "ReturnOnEquityTTM": "0.22",
    "RevenueTTM": "58080002000",
    "GrossProfitTTM": "39598000000",
    "DilutedEPSTTM": "8.83",
    "QuarterlyEarningsGrowthYOY": "0.076",
    "QuarterlyRevenueGrowthYOY": "0.099",
    "AnalystTargetPrice": "130.83",
    "AnalystRatingStrongBuy": "7",
    "AnalystRatingBuy": "13",
    "AnalystRatingHold": "6",
    "AnalystRatingSell": "0",
    "AnalystRatingStrongSell": "0",
    "TrailingPE": "11.98",
    "ForwardPE": "12.15",
    "PriceToSalesRatioTTM": "2.12",
    "PriceToBookRatio": "2.49",
    "EVToRevenue": "2.45",
    "EVToEBITDA": "5.37",
    "Beta": "1.249",
    "52WeekHigh": "134.33",
    "52WeekLow": "103.98",
    "50DayMovingAverage": "113.28",
    "200DayMovingAverage": "116.92",
    "SharesOutstanding": "1164310000",
    "DividendDate": "2024-06-03",
    "ExDividendDate": "2024-05-10"
}