{
    "Symbol": "EPD",
    "AssetType": "Common Stock",
    "Name": "Enterprise Products Partners LP",
    "Description": "Enterprise Products Partners LP provides midstream energy services to producers and consumers of natural gas, natural gas liquids (NGL), crude oil, petrochemicals, and refined products. The company is headquartered in Houston, Texas.",
    "CIK": "1061219",
    "Exchange": "NYSE",
    "Currency": "USD",
    "Country": "USA",
    "Sector": "ENERGY & TRANSPORTATION",
    "Industry": "NATURAL GAS TRANSMISSION",
    "Address": "1100 LOUISIANA 10TH FLOOR, HOUSTON, TX, US",
    "FiscalYearEnd": "December",
    "LatestQuarter": "2024-03-31",
    "MarketCapitalization": "62019752000",
    "EBITDA": "9221000000",
    "PERatio": "10.9",
    "PEGRatio": "5.13",
    "BookValue": "12.74",
    "DividendPerShare": "2.055",
    "DividendYield": "0.0735",
    "EPS": "2.62",
    "RevenuePerShareTTM": "25.27",
    "ProfitMargin": "0.105",
    "OperatingMarginTTM": "0.124",
    "ReturnOnAssetsTTM": "0.0593",
    "ReturnOnEquityTTM": "0.203",
    "RevenueTTM": "54863000000",
    "GrossProfitTTM": "6725000000",
    "DilutedEPSTTM": "2.62",
    "QuarterlyEarningsGrowthYOY": "0.121",
    "QuarterlyRevenueGrowthYOY": "0.266",
    "AnalystTargetPrice": "33.62",
    "AnalystRatingStrongBuy": "7",
    "AnalystRatingBuy": "11",
    "AnalystRatingHold": "2",
    "AnalystRatingSell": "0",
    "AnalystRatingStrongSell": "0",
    "TrailingPE": "10.9",
    "ForwardPE": "10.82",
    "PriceToSalesRatioTTM": "1.267",
    "PriceToBookRatio": "2.276",
    "EVToRevenue": "1.848",
    "EVToEBITDA": "10.16",
    "Beta": "1.014",
    "52WeekHigh": "29.52",
    "52WeekLow": "24.25",
    "50DayMovingAverage": "28.91",
    "200DayMovingAverage": "27.82",
    "SharesOutstanding": "2171560000",
    "DividendDate": "2024-08-14",
    "ExDividendDate": "2024-07-31"
}