{
    "Symbol": "EVR",
    "AssetType": "Common Stock",
    "Name": "Evercore Partners Inc",
    "Description": "Evercore Inc., is an independent investment banking advisory firm in the United States, Europe, Latin America and internationally. The company is headquartered in New York, New York.",
    "CIK": "1360901",
    "Exchange": "NYSE",
    "Currency": "USD",
    "Country": "USA",
    "Sector": "FINANCE",
    "Industry": "INVESTMENT ADVICE",
    "Address": "55 EAST 52ND STREET, 38TH FLOOR, NEW YORK, NY, US",
    "FiscalYearEnd": "December",
    "LatestQuarter": "2024-03-31",
    "MarketCapitalization": "8780991000",
    "EBITDA": "None",
    "PERatio": "31.49",
    "PEGRatio": "1.128",
    "BookValue": "37.51",
    "DividendPerShare": "3.12",
    "DividendYield": "0.0134",
    "EPS": "7.24",
    "RevenuePerShareTTM": "68.78",
    "ProfitMargin": "0.112",
    "OperatingMarginTTM": "0.157",
    "ReturnOnAssetsTTM": "0.0994",
    "ReturnOnEquityTTM": "0.178",
    "RevenueTTM": "2624426000",
    "GrossProfitTTM": "2638878000",
    "DilutedEPSTTM": "7.24",
    "QuarterlyEarningsGrowthYOY": "0.905",
    "QuarterlyRevenueGrowthYOY": "0.38",
    "AnalystTargetPrice": "257",
    "AnalystRatingStrongBuy": "1",
    "AnalystRatingBuy": "3",
    "AnalystRatingHold": "4",
    "AnalystRatingSell": "0",
    "AnalystRatingStrongSell": "0",
    "TrailingPE": "31.49",
    "ForwardPE": "25.38",
    "PriceToSalesRatioTTM": "3.346",
    "PriceToBookRatio": "6.35",
    "EVToRevenue": "3.815",
    "EVToEBITDA": "6.32",
    "Beta": "1.372",
    "52WeekHigh": "254.74",
    "52WeekLow": "122.86",
    "50DayMovingAverage": "214.46",
    "200DayMovingAverage": "182.19",
    "SharesOutstanding": "38516500",
    "DividendDate": "2024-09-13",
    "ExDividendDate": "2024-08-30"
}