{
    "Symbol": "HOOD",
    "AssetType": "Common Stock",
    "Name": "Robinhood Markets Inc",
    "Description": "None",
    "CIK": "1783879",
    "Exchange": "NASDAQ",
    "Currency": "USD",
    "Country": "USA",
    "Sector": "FINANCE",
    "Industry": "SECURITY BROKERS, DEALERS & FLOTATION COMPANIES",
    "Address": "85 WILLOW STREET, MENLO PARK, CA, US",
    "FiscalYearEnd": "December",
    "LatestQuarter": "2024-03-31",
    "MarketCapitalization": "17787640000",
    "EBITDA": "138119000",
    "PERatio": "144.57",
    "PEGRatio": "None",
    "BookValue": "7.84",
    "DividendPerShare": "None",
    "DividendYield": "None",
    "EPS": "0.14",
    "RevenuePerShareTTM": "2.306",
    "ProfitMargin": "0.0622",
    "OperatingMarginTTM": "0.256",
    "ReturnOnAssetsTTM": "0.0034",
    "ReturnOnEquityTTM": "0.0182",
    "RevenueTTM": "2042000000",
    "GrossProfitTTM": "906000000",
    "DilutedEPSTTM": "0.14",
    "QuarterlyEarningsGrowthYOY": "0",
    "QuarterlyRevenueGrowthYOY": "0.401",
    "AnalystTargetPrice": "23.37",
    "AnalystRatingStrongBuy": "2",
    "AnalystRatingBuy": "3",
    "AnalystRatingHold": "9",
    "AnalystRatingSell": "2",
    "AnalystRatingStrongSell": "1",
    "TrailingPE": "144.57",
    "ForwardPE": "-",
    "PriceToSalesRatioTTM": "10.08",
    "PriceToBookRatio": "2.989",
    "EVToRevenue": "7.59",
    "EVToEBITDA": "78.3",
    "Beta": "1.839",
    "52WeekHigh": "24.88",
    "52WeekLow": "7.91",
    "50DayMovingAverage": "22.05",
    "200DayMovingAverage": "15.66",
    "SharesOutstanding": "754860000",
    "DividendDate": "None",
    "ExDividendDate": "None"
}