{
    "Symbol": "IHG",
    "AssetType": "Common Stock",
    "Name": "InterContinental Hotels Group PLC ADR",
    "Description": "InterContinental Hotels Group PLC owns, manages, franchises, and leases hotels in the Americas, Europe, Asia, the Middle East, Africa, and Greater China. The company is headquartered in Denham, the United Kingdom.",
    "CIK": "858446",
    "Exchange": "NYSE",
    "Currency": "USD",
    "Country": "USA",
    "Sector": "REAL ESTATE & CONSTRUCTION",
    "Industry": "HOTELS & MOTELS",
    "Address": "BROADWATER PARK, DENHAM, BUCKINGHAMSHIRE, GB",
    "FiscalYearEnd": "December",
    "LatestQuarter": "2023-12-31",
    "MarketCapitalization": "16187145000",
    "EBITDA": "1056000000",
    "PERatio": "21.97",
    "PEGRatio": "1.765",
    "BookValue": "-11.84",
    "DividendPerShare": "1.523",
    "DividendYield": "0.0157",
    "EPS": "4.41",
    "RevenuePerShareTTM": "3.684",
    "ProfitMargin": "0.201",
    "OperatingMarginTTM": "0.238",
    "ReturnOnAssetsTTM": "0.142",
    "ReturnOnEquityTTM": "0",
    "RevenueTTM": "3728000000",
    "GrossProfitTTM": "1498000000",
    "DilutedEPSTTM": "4.41",
    "QuarterlyEarningsGrowthYOY": "0.976",
    "QuarterlyRevenueGrowthYOY": "0.169",
    "AnalystTargetPrice": "96.72",
    "AnalystRatingStrongBuy": "1",
    "AnalystRatingBuy": "0",
    "AnalystRatingHold": "0",
    "AnalystRatingSell": "0",
    "AnalystRatingStrongSell": "0",
    "TrailingPE": "21.97",
    "ForwardPE": "22.94",
    "PriceToSalesRatioTTM": "7.48",
    "PriceToBookRatio": "-",
    "EVToRevenue": "3.967",
    "EVToEBITDA": "14.39",
    "Beta": "1.014",
    "52WeekHigh": "111.51",
    "52WeekLow": "69.36",
    "50DayMovingAverage": "104.01",
    "200DayMovingAverage": "95.7",
    "SharesOutstanding": "160787000",
    "DividendDate": "2024-05-14",
    "ExDividendDate": "2024-04-04"
}