{
    "Symbol": "KOF",
    "AssetType": "Common Stock",
    "Name": "Coca-Cola Femsa SAB de CV ADR",
    "Description": "Coca-Cola FEMSA, SAB de CV, a franchise bottler, produces, markets, sells and distributes Coca-Cola brand beverages. The company is headquartered in Mexico City, Mexico.",
    "CIK": "910631",
    "Exchange": "NYSE",
    "Currency": "USD",
    "Country": "USA",
    "Sector": "MANUFACTURING",
    "Industry": "BOTTLED & CANNED SOFT DRINKS & CARBONATED WATERS",
    "Address": "MARIO PANI #100, PISO 7, COL SANTA FE, CUAJIMALPA, MX",
    "FiscalYearEnd": "December",
    "LatestQuarter": "2024-06-30",
    "MarketCapitalization": "18907458000",
    "EBITDA": "44601500000",
    "PERatio": "83.32",
    "PEGRatio": "16.28",
    "BookValue": "609.96",
    "DividendPerShare": "60.8",
    "DividendYield": "0.0198",
    "EPS": "1.06",
    "RevenuePerShareTTM": "1238.36",
    "ProfitMargin": "0.0819",
    "OperatingMarginTTM": "0.138",
    "ReturnOnAssetsTTM": "0.0803",
    "ReturnOnEquityTTM": "0.171",
    "RevenueTTM": "260132127000",
    "GrossProfitTTM": "100299573000",
    "DilutedEPSTTM": "1.06",
    "QuarterlyEarningsGrowthYOY": "0.138",
    "QuarterlyRevenueGrowthYOY": "0.131",
    "AnalystTargetPrice": "100.17",
    "AnalystRatingStrongBuy": "2",
    "AnalystRatingBuy": "5",
    "AnalystRatingHold": "3",
    "AnalystRatingSell": "0",
    "AnalystRatingStrongSell": "0",
    "TrailingPE": "83.32",
    "ForwardPE": "111.11",
    "PriceToSalesRatioTTM": "0.0832",
    "PriceToBookRatio": "2.647",
    "EVToRevenue": "0.0905",
    "EVToEBITDA": "0.614",
    "Beta": "0.866",
    "52WeekHigh": "102.4",
    "52WeekLow": "66.63",
    "50DayMovingAverage": "87.95",
    "200DayMovingAverage": "91.08",
    "SharesOutstanding": "210083000",
    "DividendDate": "2024-07-26",
    "ExDividendDate": "2024-07-15"
}