{
    "Symbol": "MTZ",
    "AssetType": "Common Stock",
    "Name": "MasTec Inc",
    "Description": "MasTec, Inc., an infrastructure construction company, provides engineering, construction, installation, maintenance, and upgrade services for communications, energy, utilities, and other infrastructure primarily in the United States and Canada. The company is headquartered in Coral Gables, Florida.",
    "CIK": "15615",
    "Exchange": "NYSE",
    "Currency": "USD",
    "Country": "USA",
    "Sector": "REAL ESTATE & CONSTRUCTION",
    "Industry": "WATER, SEWER, PIPELINE, COMM & POWER LINE CONSTRUCTION",
    "Address": "800 S. DOUGLAS ROAD, 12TH FLOOR, CORAL GABLES, FL, US",
    "FiscalYearEnd": "December",
    "LatestQuarter": "2024-03-31",
    "MarketCapitalization": "8432125000",
    "EBITDA": "818463000",
    "PERatio": "None",
    "PEGRatio": "1.508",
    "BookValue": "34.33",
    "DividendPerShare": "None",
    "DividendYield": "None",
    "EPS": "-0.12",
    "RevenuePerShareTTM": "155.55",
    "ProfitMargin": "-0.0009",
    "OperatingMarginTTM": "0.0002",
    "ReturnOnAssetsTTM": "0.0157",
    "ReturnOnEquityTTM": "-0.0005",
    "RevenueTTM": "12098124000",
    "GrossProfitTTM": "1221005000",
    "DilutedEPSTTM": "-0.12",
    "QuarterlyEarningsGrowthYOY": "-0.877",
    "QuarterlyRevenueGrowthYOY": "0.04",
    "AnalystTargetPrice": "122",
    "AnalystRatingStrongBuy": "3",
    "AnalystRatingBuy": "7",
    "AnalystRatingHold": "3",
    "AnalystRatingSell": "0",
    "AnalystRatingStrongSell": "0",
    "TrailingPE": "-",
    "ForwardPE": "30.77",
    "PriceToSalesRatioTTM": "0.583",
    "PriceToBookRatio": "2.584",
    "EVToRevenue": "0.83",
    "EVToEBITDA": "13.19",
    "Beta": "1.653",
    "52WeekHigh": "113.12",
    "52WeekLow": "44.65",
    "50DayMovingAverage": "107.49",
    "200DayMovingAverage": "83.43",
    "SharesOutstanding": "79458000",
    "DividendDate": "None",
    "ExDividendDate": "1982-08-04"
}