{
    "Symbol": "PUK",
    "AssetType": "Common Stock",
    "Name": "Prudential Public Limited Company",
    "Description": "Prudential plc offers life and health insurance, retirement and asset management solutions to people in Asia, the United States and Africa. The company is headquartered in London, the United Kingdom.",
    "CIK": "1116578",
    "Exchange": "NYSE",
    "Currency": "USD",
    "Country": "USA",
    "Sector": "FINANCE",
    "Industry": "LIFE INSURANCE",
    "Address": "LAURENCE POUNTNEY HILL, LONDON, GB",
    "FiscalYearEnd": "December",
    "LatestQuarter": "2023-12-31",
    "MarketCapitalization": "24553255000",
    "EBITDA": "4183000000",
    "PERatio": "13.72",
    "PEGRatio": "0.392",
    "BookValue": "6.5",
    "DividendPerShare": "0.205",
    "DividendYield": "0.0241",
    "EPS": "1.24",
    "RevenuePerShareTTM": "2.014",
    "ProfitMargin": "0.154",
    "OperatingMarginTTM": "0.339",
    "ReturnOnAssetsTTM": "0.014",
    "ReturnOnEquityTTM": "0.0982",
    "RevenueTTM": "11038000000",
    "GrossProfitTTM": "3742000000",
    "DilutedEPSTTM": "1.24",
    "QuarterlyEarningsGrowthYOY": "0.498",
    "QuarterlyRevenueGrowthYOY": "0.004",
    "AnalystTargetPrice": "26.3",
    "AnalystRatingStrongBuy": "1",
    "AnalystRatingBuy": "0",
    "AnalystRatingHold": "0",
    "AnalystRatingSell": "0",
    "AnalystRatingStrongSell": "0",
    "TrailingPE": "13.72",
    "ForwardPE": "11.34",
    "PriceToSalesRatioTTM": "2.238",
    "PriceToBookRatio": "1.351",
    "EVToRevenue": "2.312",
    "EVToEBITDA": "-",
    "Beta": "1.262",
    "52WeekHigh": "26.4",
    "52WeekLow": "16.57",
    "50DayMovingAverage": "18.67",
    "200DayMovingAverage": "20.17",
    "SharesOutstanding": "1367880000",
    "DividendDate": "2024-05-16",
    "ExDividendDate": "2024-04-01"
}