{
    "Symbol": "QRVO",
    "AssetType": "Common Stock",
    "Name": "Qorvo Inc",
    "Description": "Qorvo is an American semiconductor company that designs, manufactures, and supplies radio-frequency systems for applications that drive wireless and broadband communications, as well as foundry services.",
    "CIK": "1604778",
    "Exchange": "NASDAQ",
    "Currency": "USD",
    "Country": "USA",
    "Sector": "MANUFACTURING",
    "Industry": "SEMICONDUCTORS & RELATED DEVICES",
    "Address": "7628 THORNDIKE ROAD, GREENSBORO, NC, US",
    "FiscalYearEnd": "March",
    "LatestQuarter": "2024-06-30",
    "MarketCapitalization": "10496402000",
    "EBITDA": "761272000",
    "PERatio": "None",
    "PEGRatio": "0.468",
    "BookValue": "36.71",
    "DividendPerShare": "None",
    "DividendYield": "None",
    "EPS": "-0.28",
    "RevenuePerShareTTM": "41.38",
    "ProfitMargin": "-0.0066",
    "OperatingMarginTTM": "0.0057",
    "ReturnOnAssetsTTM": "0.0424",
    "ReturnOnEquityTTM": "-0.0072",
    "RevenueTTM": "4005013000",
    "GrossProfitTTM": "1296942000",
    "DilutedEPSTTM": "-0.28",
    "QuarterlyEarningsGrowthYOY": "-0.456",
    "QuarterlyRevenueGrowthYOY": "0.362",
    "AnalystTargetPrice": "125.56",
    "AnalystRatingStrongBuy": "1",
    "AnalystRatingBuy": "6",
    "AnalystRatingHold": "18",
    "AnalystRatingSell": "2",
    "AnalystRatingStrongSell": "1",
    "TrailingPE": "-",
    "ForwardPE": "15.13",
    "PriceToSalesRatioTTM": "3.106",
    "PriceToBookRatio": "2.955",
    "EVToRevenue": "3.383",
    "EVToEBITDA": "49.28",
    "Beta": "1.461",
    "52WeekHigh": "130.99",
    "52WeekLow": "80.62",
    "50DayMovingAverage": "112.75",
    "200DayMovingAverage": "106.82",
    "SharesOutstanding": "94861000",
    "DividendDate": "None",
    "ExDividendDate": "None"
}