{
    "Symbol": "SYF",
    "AssetType": "Common Stock",
    "Name": "Synchrony Financial",
    "Description": "Synchrony Financial is a consumer financial services company headquartered in Stamford, Connecticut, United States. The company offers consumer financing products, including credit, promotional financing and loyalty programs, installment lending to industries, and FDIC-insured consumer savings products through Synchrony Bank, its wholly owned online bank subsidiary.",
    "CIK": "1601712",
    "Exchange": "NYSE",
    "Currency": "USD",
    "Country": "USA",
    "Sector": "FINANCE",
    "Industry": "FINANCE SERVICES",
    "Address": "777 LONG RIDGE ROAD, STAMFORD, CT, US",
    "FiscalYearEnd": "December",
    "LatestQuarter": "2024-06-30",
    "MarketCapitalization": "19192224000",
    "EBITDA": "None",
    "PERatio": "6.78",
    "PEGRatio": "1.792",
    "BookValue": "36.24",
    "DividendPerShare": "1",
    "DividendYield": "0.0206",
    "EPS": "7.16",
    "RevenuePerShareTTM": "21.27",
    "ProfitMargin": "0.342",
    "OperatingMarginTTM": "0.418",
    "ReturnOnAssetsTTM": "0.0262",
    "ReturnOnEquityTTM": "0.208",
    "RevenueTTM": "8777000000",
    "GrossProfitTTM": "8299000000",
    "DilutedEPSTTM": "7.16",
    "QuarterlyEarningsGrowthYOY": "0.174",
    "QuarterlyRevenueGrowthYOY": "0.058",
    "AnalystTargetPrice": "55.29",
    "AnalystRatingStrongBuy": "3",
    "AnalystRatingBuy": "7",
    "AnalystRatingHold": "9",
    "AnalystRatingSell": "1",
    "AnalystRatingStrongSell": "0",
    "TrailingPE": "6.78",
    "ForwardPE": "7.35",
    "PriceToSalesRatioTTM": "2.146",
    "PriceToBookRatio": "1.248",
    "EVToRevenue": "-",
    "EVToEBITDA": "-",
    "Beta": "1.63",
    "52WeekHigh": "52.67",
    "52WeekLow": "26.73",
    "50DayMovingAverage": "46.44",
    "200DayMovingAverage": "40.03",
    "SharesOutstanding": "395227000",
    "DividendDate": "2024-08-15",
    "ExDividendDate": "2024-08-05"
}