{
    "Symbol": "TDG",
    "AssetType": "Common Stock",
    "Name": "Transdigm Group Incorporated",
    "Description": "TransDigm Group is a publicly traded aerospace manufacturing company headquartered in Cleveland, Ohio. TransDigm develops and manufactures engineered aerospace components.",
    "CIK": "1260221",
    "Exchange": "NYSE",
    "Currency": "USD",
    "Country": "USA",
    "Sector": "MANUFACTURING",
    "Industry": "AIRCRAFT PARTS & AUXILIARY EQUIPMENT, NEC",
    "Address": "1301 EAST 9TH STREET, SUITE 3710, CLEVELAND, OH, US",
    "FiscalYearEnd": "September",
    "LatestQuarter": "2024-03-31",
    "MarketCapitalization": "70957621000",
    "EBITDA": "3604000000",
    "PERatio": "50.26",
    "PEGRatio": "4.789",
    "BookValue": "-54.15",
    "DividendPerShare": "0",
    "DividendYield": "0",
    "EPS": "25.23",
    "RevenuePerShareTTM": "126.92",
    "ProfitMargin": "0.212",
    "OperatingMarginTTM": "0.459",
    "ReturnOnAssetsTTM": "0.0999",
    "ReturnOnEquityTTM": "0",
    "RevenueTTM": "7304000000",
    "GrossProfitTTM": "3842000000",
    "DilutedEPSTTM": "25.23",
    "QuarterlyEarningsGrowthYOY": "0.31",
    "QuarterlyRevenueGrowthYOY": "0.205",
    "AnalystTargetPrice": "1462.59",
    "AnalystRatingStrongBuy": "6",
    "AnalystRatingBuy": "13",
    "AnalystRatingHold": "6",
    "AnalystRatingSell": "0",
    "AnalystRatingStrongSell": "0",
    "TrailingPE": "50.26",
    "ForwardPE": "38.31",
    "PriceToSalesRatioTTM": "9.73",
    "PriceToBookRatio": "-",
    "EVToRevenue": "12.06",
    "EVToEBITDA": "26.13",
    "Beta": "1.382",
    "52WeekHigh": "1369.58",
    "52WeekLow": "774.0",
    "50DayMovingAverage": "1293.11",
    "200DayMovingAverage": "1140.35",
    "SharesOutstanding": "55958000",
    "DividendDate": "2023-11-27",
    "ExDividendDate": "2023-11-17"
}