{
    "Symbol": "USB",
    "AssetType": "Common Stock",
    "Name": "U.S. Bancorp",
    "Description": "U.S. Bancorp is an American bank holding company based in Minneapolis, Minnesota, and incorporated in Delaware. The company provides banking, investment, mortgage, trust, and payment services products to individuals, businesses, governmental entities, and other financial institutions.",
    "CIK": "36104",
    "Exchange": "NYSE",
    "Currency": "USD",
    "Country": "USA",
    "Sector": "FINANCE",
    "Industry": "NATIONAL COMMERCIAL BANKS",
    "Address": "U.S. BANCORP, 800 NICOLLET MALL, MINNEAPOLIS, MN, US",
    "FiscalYearEnd": "December",
    "LatestQuarter": "2024-03-31",
    "MarketCapitalization": "67848802000",
    "EBITDA": "None",
    "PERatio": "13.8",
    "PEGRatio": "1.137",
    "BookValue": "31.8",
    "DividendPerShare": "1.95",
    "DividendYield": "0.0451",
    "EPS": "3.15",
    "RevenuePerShareTTM": "16.12",
    "ProfitMargin": "0.211",
    "OperatingMarginTTM": "0.351",
    "ReturnOnAssetsTTM": "0.0078",
    "ReturnOnEquityTTM": "0.0964",
    "RevenueTTM": "25106000000",
    "GrossProfitTTM": "22142000000",
    "DilutedEPSTTM": "3.15",
    "QuarterlyEarningsGrowthYOY": "0.161",
    "QuarterlyRevenueGrowthYOY": "-0.008",
    "AnalystTargetPrice": "49.72",
    "AnalystRatingStrongBuy": "4",
    "AnalystRatingBuy": "7",
    "AnalystRatingHold": "15",
    "AnalystRatingSell": "0",
    "AnalystRatingStrongSell": "0",
    "TrailingPE": "13.8",
    "ForwardPE": "10.68",
    "PriceToSalesRatioTTM": "2.518",
    "PriceToBookRatio": "1.336",
    "EVToRevenue": "-",
    "EVToEBITDA": "-",
    "Beta": "1.061",
    "52WeekHigh": "45.88",
    "52WeekLow": "29.42",
    "50DayMovingAverage": "41.11",
    "200DayMovingAverage": "40.57",
    "SharesOutstanding": "1560460000",
    "DividendDate": "2024-07-15",
    "ExDividendDate": "2024-06-28"
}